{"groups": [], "environmentKey": "production", "rollouts": [{"experiments": [{"status": "Running", "audienceIds": [], "variations": [{"variables": [], "id": "20367968376", "key": "20367968376", "featureEnabled": true}], "id": "20366186459", "key": "20366186459", "layerId": "20385187331", "trafficAllocation": [{"entityId": "20367968376", "endOfRange": 10000}], "forcedVariations": {}}], "id": "20385187331"}, {"experiments": [{"status": "Running", "audienceIds": [], "variations": [{"variables": [{"id": "20056142603", "value": "{}"}, {"id": "19571855438", "value": "{}"}, {"id": "20167580332", "value": "{}"}, {"id": "19605374796", "value": "{}"}, {"id": "20109294939", "value": "{}"}], "id": "19605454622", "key": "19605454622", "featureEnabled": true}], "id": "19675531743", "key": "19675531743", "layerId": "19650161770", "trafficAllocation": [{"entityId": "19605454622", "endOfRange": 10000}], "forcedVariations": {}}], "id": "19650161770"}, {"experiments": [{"status": "Running", "audienceIds": [], "variations": [{"variables": [{"id": "19044740852", "value": "{}"}], "id": "19050510809", "key": "19050510809", "featureEnabled": true}], "id": "19079600534", "key": "19079600534", "layerId": "19079420495", "trafficAllocation": [], "forcedVariations": {}}], "id": "19079420495"}, {"experiments": [{"status": "Running", "audienceIds": [], "variations": [{"variables": [], "id": "20397371777", "key": "20397371777", "featureEnabled": true}], "id": "20373812769", "key": "20373812769", "layerId": "20393513588", "trafficAllocation": [{"entityId": "20397371777", "endOfRange": 10000}], "forcedVariations": {}}], "id": "20393513588"}, {"experiments": [{"status": "Running", "audienceIds": [], "variations": [{"variables": [], "id": "21316172273", "key": "21316172273", "featureEnabled": true}], "id": "21341031549", "key": "21341031549", "layerId": "21354971287", "trafficAllocation": [], "forcedVariations": {}}], "id": "21354971287"}, {"experiments": [{"status": "Running", "audienceIds": [], "variations": [{"variables": [{"id": "21660420181", "value": "{}"}, {"id": "20770552185", "value": "{}"}, {"id": "20643880129", "value": "{}"}, {"id": "21628510689", "value": "{}"}, {"id": "22025632851", "value": "{}"}, {"id": "20618050263", "value": "{}"}, {"id": "21904511441", "value": "{}"}, {"id": "20622850167", "value": "{}"}, {"id": "21142460348", "value": "{}"}, {"id": "20691220938", "value": "{}"}, {"id": "20647400094", "value": "{}"}, {"id": "21275920011", "value": "{}"}, {"id": "21134900381", "value": "{}"}, {"id": "20520622729", "value": "{}"}, {"id": "20639410267", "value": "{}"}, {"id": "21268770003", "value": "{}"}, {"id": "20628270213", "value": "{}"}, {"id": "20719300839", "value": "{}"}, {"id": "21287371349", "value": "{}"}, {"id": "21179472018", "value": "{}"}, {"id": "21230332381", "value": "{}"}, {"id": "21157261168", "value": "{}"}, {"id": "21242072297", "value": "{}"}, {"id": "20626280128", "value": "{}"}, {"id": "21651650291", "value": "{}"}, {"id": "21352850187", "value": "{}"}, {"id": "20626150155", "value": "{}"}, {"id": "20640280014", "value": "{}"}, {"id": "21134770537", "value": "{}"}, {"id": "21260940456", "value": "{}"}, {"id": "21604363711", "value": "{}"}, {"id": "20649000172", "value": "{}"}, {"id": "20715381351", "value": "{}"}], "id": "20551472610", "key": "20551472610", "featureEnabled": true}], "id": "20536372701", "key": "20536372701", "layerId": "20544232732", "trafficAllocation": [{"entityId": "20551472610", "endOfRange": 10000}], "forcedVariations": {}}], "id": "20544232732"}], "typedAudiences": [], "projectId": "17281321285", "variables": [], "featureFlags": [{"experimentIds": [], "rolloutId": "19079420495", "variables": [{"subType": "json", "defaultValue": "{}", "type": "string", "id": "19044740852", "key": "CONTEXT_DEFAULT"}], "id": "19046620864", "key": "RAAS_WEB_GNAV"}, {"experimentIds": [], "rolloutId": "19650161770", "variables": [{"subType": "json", "defaultValue": "{}", "type": "string", "id": "19571855438", "key": "CONTEXT_SAVE_SEARCH"}, {"subType": "json", "defaultValue": "{}", "type": "string", "id": "19605374796", "key": "CONTEXT_SAVE_HOME"}, {"subType": "json", "defaultValue": "{}", "type": "string", "id": "20056142603", "key": "CONTEXT_CLAIM_HOME"}, {"subType": "json", "defaultValue": "{}", "type": "string", "id": "20109294939", "key": "CONTEXT_OPEN_HOUSE_LS"}, {"subType": "json", "defaultValue": "{}", "type": "string", "id": "20167580332", "key": "CONTEXT_SAVE_RECENT_SEARCH"}], "id": "19609563900", "key": "RAAS_WEB_SWAP"}, {"experimentIds": [], "rolloutId": "20385187331", "variables": [], "id": "20387750964", "key": "ENABLE_ENHANCED_ADD_PWD"}, {"experimentIds": [], "rolloutId": "20393513588", "variables": [], "id": "20391802546", "key": "ENABLE_ENHANCED_RESET_PWD"}, {"experimentIds": ["20538072546"], "rolloutId": "20544232732", "variables": [{"subType": "json", "defaultValue": "{}", "type": "string", "id": "20520622729", "key": "CONTEXT_GNAV_LOGIN"}, {"subType": "json", "defaultValue": "{}", "type": "string", "id": "20618050263", "key": "CONTEXT_SAVE_SEARCH"}, {"subType": "json", "defaultValue": "{}", "type": "string", "id": "20622850167", "key": "CONTEXT_CLAIM_HOME"}, {"subType": "json", "defaultValue": "{}", "type": "string", "id": "20626150155", "key": "CONTEXT_RENTAL_SAVE_HOME"}, {"subType": "json", "defaultValue": "{}", "type": "string", "id": "20626280128", "key": "CONTEXT_BZ_REG_SAVE_SEARCH"}, {"subType": "json", "defaultValue": "{}", "type": "string", "id": "20628270213", "key": "CONTEXT_OPEN_HOUSE_LS"}, {"subType": "json", "defaultValue": "{}", "type": "string", "id": "20639410267", "key": "CONTEXT_RENTAL_SAVE_SEARCH"}, {"subType": "json", "defaultValue": "{}", "type": "string", "id": "20640280014", "key": "CONTEXT_SAVE_RECENT_SEARCH"}, {"subType": "json", "defaultValue": "{}", "type": "string", "id": "20643880129", "key": "CONTEXT_OPEN_HOUSE_IP"}, {"subType": "json", "defaultValue": "{}", "type": "string", "id": "20647400094", "key": "CONTEXT_SAVE_HOME"}, {"subType": "json", "defaultValue": "{}", "type": "string", "id": "20649000172", "key": "CONTEXT_GNAV_SIGNUP"}, {"subType": "json", "defaultValue": "{}", "type": "string", "id": "20691220938", "key": "CONTEXT_COLLABORATE"}, {"subType": "json", "defaultValue": "{}", "type": "string", "id": "20715381351", "key": "CONTEXT_HIDE_HOME"}, {"subType": "json", "defaultValue": "{}", "type": "string", "id": "20719300839", "key": "CONTEXT_ADDAMS_FAMILY_SWEEPSTAKES"}, {"subType": "json", "defaultValue": "{}", "type": "string", "id": "20770552185", "key": "CONTEXT_COLLABORATE_FEEDBACK_REQUEST"}, {"subType": "json", "defaultValue": "{}", "type": "string", "id": "21134770537", "key": "CONTEXT_NEWS_AND_INSIGHTS_CELEBRITY_REAL_ESTATE"}, {"subType": "json", "defaultValue": "{}", "type": "string", "id": "21134900381", "key": "CONTEXT_NEWS_AND_INSIGHTS_TRENDS"}, {"subType": "json", "defaultValue": "{}", "type": "string", "id": "21142460348", "key": "CONTEXT_NEWS_AND_INSIGHTS_UNIQUE_HOMES"}, {"subType": "json", "defaultValue": "{}", "type": "string", "id": "21157261168", "key": "CONTEXT_HIGHRISES"}, {"subType": "json", "defaultValue": "{}", "type": "string", "id": "21179472018", "key": "CONTEXT_DYNAMIC_CONTENT_ZONE"}, {"subType": "json", "defaultValue": "{}", "type": "string", "id": "21230332381", "key": "CONTEXT_EBOOK_EN"}, {"subType": "json", "defaultValue": "{}", "type": "string", "id": "21242072297", "key": "CONTEXT_EBOOK_SP"}, {"subType": "json", "defaultValue": "{}", "type": "string", "id": "21260940456", "key": "CONTEXT_BZ_REG_TEST"}, {"subType": "json", "defaultValue": "{}", "type": "string", "id": "21268770003", "key": "CONTEXT_PDP_CLAIM_HOME_EDIT_FACTS"}, {"subType": "json", "defaultValue": "{}", "type": "string", "id": "21275920011", "key": "CONTEXT_PDP_CLAIM_HOME"}, {"subType": "json", "defaultValue": "{}", "type": "string", "id": "21287371349", "key": "CONTEXT_NEWS_AND_INSIGHTS_SIGNUP"}, {"subType": "json", "defaultValue": "{}", "type": "string", "id": "21352850187", "key": "CONTEXT_BZ_REG_NEXT_BEST_ACTION"}, {"subType": "json", "defaultValue": "{}", "type": "string", "id": "21604363711", "key": "CONTEXT_BZ_REG_BE_FIRST_TO_KNOW"}, {"subType": "json", "defaultValue": "{}", "type": "string", "id": "21628510689", "key": "CONTEXT_BZ_REG_SYNC_YOUR_SEARCH"}, {"subType": "json", "defaultValue": "{}", "type": "string", "id": "21651650291", "key": "CONTEXT_BZ_REG_FIND_HOME_TOGETHER"}, {"subType": "json", "defaultValue": "{}", "type": "string", "id": "21660420181", "key": "CONTEXT_CLAIM_HOME_IN_APP_WEB"}, {"subType": "json", "defaultValue": "{}", "type": "string", "id": "21904511441", "key": "CONTEXT_BZ_REG_JOIN_THE_SMART_SEARCH"}, {"subType": "json", "defaultValue": "{}", "type": "string", "id": "22025632851", "key": "CONTEXT_RENTSWEEPS"}], "id": "20553662532", "key": "RAAS_WEB_DYNAMIC"}, {"experimentIds": [], "rolloutId": "21354971287", "variables": [], "id": "21332381063", "key": "ENABLE_FIND_STATUS_BY_EMAIL"}], "experiments": [{"status": "Running", "audienceIds": [], "variations": [{"variables": [], "id": "20539731161", "key": "C", "featureEnabled": false}, {"variables": [{"id": "21660420181", "value": "{\"landingPage\":{\"headerTitle\":\"Log in or create an account to claim your home\",\"headerDescription\":\"With accurate home details, get regular updates on its true value and monitor the local market.\",\"showProfessionalLogin\":false,\"showTermsAndPolicy\":true,\"showEmailMeLinkBtn\":false},\"passwordPage\":{\"signUp\":{\"headerTitle\":\"Add a password\",\"headerDescription\":\"Set a password to access your account on all your devices.\",\"showProfessionalLogin\":false,\"showTermsAndPolicy\":false,\"showEmailMeLinkBtn\":false},\"signIn\":{\"headerTitle\":\"Welcome back!\",\"headerDescription\":\"Please enter the password associated with {{email}} to continue.\",\"showProfessionalLogin\":false,\"showTermsAndPolicy\":false,\"showEmailMeLinkBtn\":false},\"WelcomeBack\":{\"headerTitle\":\"Welcome back!\",\"headerDescription\":\"We notice you haven't added the password yet.You'll need one to continue.\",\"showProfessionalLogin\":false,\"showTermsAndPolicy\":false,\"showEmailMeLinkBtn\":false}},\"marketingOptIn\":{\"headerTitle\":\"Thanks for signing up with realtor.com\",\"headerDescription\":\"Stay up to date with the latest tips, news, and insights on the real estate market.\",\"showProfessionalLogin\":false,\"showTermsAndPolicy\":false},\"forgotPassword\":{\"headerTitle\":\"Forgot Password?\",\"headerDescription\":\"No problem! We'll send an email with a link to reset your password.\",\"showProfessionalLogin\":false,\"showTermsAndPolicy\":false},\"almostDone\":{\"headerTitle\":\"Almost done!\",\"headerDescription\":\"Please check your inbox for password reset instructions.Don't see the email? Be sure to check your spam folder.\",\"showProfessionalLogin\":false,\"showTermsAndPolicy\":false},\"emailMeLink\":{\"headerTitle\":\"Email me a Link\",\"headerDescription\":\"Enter your email address and we will send you a link. Follow the link to sign in automatically.\",\"showProfessionalLogin\":false,\"showTermsAndPolicy\":false},\"almostDoneEmailMe\":{\"headerTitle\":\"Almost done!\",\"headerDescription\":\"Please check your inbox for a sign-in link. Follow the link in the email message to be automatically signed in. Don't see the email? Be sure to check your spam folder.\",\"showProfessionalLogin\":false,\"showTermsAndPolicy\":false},\"show_custom_html\":false,\"containerName\":\"context_aware_web\",\"canSkipAddPassword\":false,\"buttonsDisplayOrder\":[{\"key\":\"continue\",\"text\":\"Continue\"}]}"}, {"id": "20770552185", "value": "{\"landingPage\":{\"headerTitle\":\"Log in or create an account to share!\",\"headerDescription\":\"Sign up for a free Realtor.com account, then use the 'Share' button on your favorite listings to request feedback!\",\"showProfessionalLogin\":false,\"showTermsAndPolicy\":true},\"passwordPage\":{\"signUp\":{\"headerTitle\":\"Add a password\",\"headerDescription\":\"Set a password to access your account on all your devices.\",\"showProfessionalLogin\":false,\"showTermsAndPolicy\":false},\"signIn\":{\"headerTitle\":\"Welcome back!\",\"headerDescription\":\"Please enter the password associated with {{email}} to continue.\",\"showProfessionalLogin\":false,\"showTermsAndPolicy\":false},\"WelcomeBack\":{\"headerTitle\":\"Welcome back!\",\"headerDescription\":\"We notice you haven't added the password yet.You'll need one to continue.\",\"showProfessionalLogin\":false,\"showTermsAndPolicy\":false}},\"marketingOptIn\":{\"headerTitle\":\"Thanks for signing up with realtor.com\",\"headerDescription\":\"Stay up to date with the latest tips, news, and insights on the real estate market.\",\"showProfessionalLogin\":false,\"showTermsAndPolicy\":false},\"forgotPassword\":{\"headerTitle\":\"Forgot Password?\",\"headerDescription\":\"No problem! We'll send an email with a link to reset your password.\",\"showProfessionalLogin\":false,\"showTermsAndPolicy\":false},\"almostDone\":{\"headerTitle\":\"Almost done!\",\"headerDescription\":\"Please check your inbox for password reset instructions.Don't see the email? Be sure to check your spam folder.\",\"showProfessionalLogin\":false,\"showTermsAndPolicy\":false},\"show_custom_html\":false,\"containerName\":\"context_aware_web\",\"canSkipAddPassword\":false,\"buttonsDisplayOrder\":[{\"key\":\"continue\",\"text\":\"Continue\"},{\"key\":\"google\",\"text\":\"Continue with Google\"},{\"key\":\"facebook\",\"text\":\"Continue with Facebook\"},{\"key\":\"apple\",\"text\":\"Continue with Apple\"}]}"}, {"id": "20643880129", "value": "{\"landingPage\":{\"headerTitle\":\"Login or create an account to attend this event\",\"headerDescription\":\"Schedule your In-Person Open House event and we'll add it to your saved homes.\",\"showProfessionalLogin\":false,\"showTermsAndPolicy\":true,\"showEmailMeLinkBtn\":true},\"passwordPage\":{\"signUp\":{\"headerTitle\":\"Add a password\",\"headerDescription\":\"Set a password to access your account on all your devices.\",\"showProfessionalLogin\":false,\"showTermsAndPolicy\":false,\"showEmailMeLinkBtn\":true},\"signIn\":{\"headerTitle\":\"Welcome back!\",\"headerDescription\":\"Please enter the password associated with {{email}} to continue.\",\"showProfessionalLogin\":false,\"showTermsAndPolicy\":false,\"showEmailMeLinkBtn\":true},\"WelcomeBack\":{\"headerTitle\":\"Welcome back!\",\"headerDescription\":\"We notice you haven't added the password yet. You'll need one to continue.\",\"showProfessionalLogin\":false,\"showTermsAndPolicy\":false,\"showEmailMeLinkBtn\":true}},\"marketingOptIn\":{\"headerTitle\":\"Thanks for signing up with realtor.com\",\"headerDescription\":\"Stay up to date with the latest tips, news, and insights on the real estate market.\",\"showProfessionalLogin\":false,\"showTermsAndPolicy\":false},\"forgotPassword\":{\"headerTitle\":\"Forgot Password?\",\"headerDescription\":\"No problem! We'll send an email with a link to reset your password.\",\"showProfessionalLogin\":false,\"showTermsAndPolicy\":false},\"almostDone\":{\"headerTitle\":\"Almost done!\",\"headerDescription\":\"Please check your inbox for password reset instructions. Don't see the email? Be sure to check your spam folder.\",\"showProfessionalLogin\":false,\"showTermsAndPolicy\":false},\"emailMeLink\":{\"headerTitle\":\"Email Me a Link\",\"headerDescription\":\"Enter your email address and we will send you a link. Follow the link to sign in automatically.\",\"showProfessionalLogin\":false,\"showTermsAndPolicy\":false},\"almostDoneEmailMe\":{\"headerTitle\":\"Almost done!\",\"headerDescription\":\"Please check your inbox for a sign-in link. Follow the link in the email message to be automatically signed in. Don't see the email? Be sure to check your spam folder.\",\"showProfessionalLogin\":false,\"showTermsAndPolicy\":false},\"show_custom_html\":false,\"containerName\":\"context_aware_web\",\"canSkipAddPassword\":true,\"buttonsDisplayOrder\":[{\"key\":\"continue\",\"text\":\"Continue\"},{\"key\":\"google\",\"text\":\"Continue with Google\"},{\"key\":\"facebook\",\"text\":\"Continue with Facebook\"},{\"key\":\"apple\",\"text\":\"Continue with Apple\"},{\"key\":\"emailMe\",\"text\":\"Email Me a Link\"}]}"}, {"id": "21628510689", "value": "{\"landingPage\":{\"headerTitle\":\"Search at home or on the go\",\"headerDescription\":\"Sign up for a free Realtor.com account to see favorite listings across all your devices.\",\"showProfessionalLogin\":true,\"showTermsAndPolicy\":true,\"showEmailMeLinkBtn\":true},\"passwordPage\":{\"signUp\":{\"headerTitle\":\"Add a password\",\"headerDescription\":\"Set a password to access your account on all your devices.\",\"showProfessionalLogin\":false,\"showTermsAndPolicy\":false,\"showEmailMeLinkBtn\":true},\"signIn\":{\"headerTitle\":\"Welcome back!\",\"headerDescription\":\"Please enter the password associated with {{email}} to continue.\",\"showProfessionalLogin\":false,\"showTermsAndPolicy\":false,\"showEmailMeLinkBtn\":true},\"WelcomeBack\":{\"headerTitle\":\"Welcome back!\",\"headerDescription\":\"We notice you haven't added the password yet.You'll need one to continue.\",\"showProfessionalLogin\":false,\"showTermsAndPolicy\":false,\"showEmailMeLinkBtn\":true}},\"marketingOptIn\":{\"headerTitle\":\"Thanks for signing up with realtor.com\",\"headerDescription\":\"Stay up to date with the latest tips, news, and insights on the real estate market.\",\"showProfessionalLogin\":false,\"showTermsAndPolicy\":false},\"forgotPassword\":{\"headerTitle\":\"Forgot Password?\",\"headerDescription\":\"No problem! We'll send an email with a link to reset your password.\",\"showProfessionalLogin\":false,\"showTermsAndPolicy\":false},\"almostDone\":{\"headerTitle\":\"Almost done!\",\"headerDescription\":\"Please check your inbox for password reset instructions. Don't see the email? Be sure to check your spam folder.\",\"showProfessionalLogin\":false,\"showTermsAndPolicy\":false},\"emailMeLink\":{\"headerTitle\":\"Email Me a Link\",\"headerDescription\":\"Enter your email address and we will send you a link. Follow the link to sign in automatically.\",\"showProfessionalLogin\":false,\"showTermsAndPolicy\":false},\"almostDoneEmailMe\":{\"headerTitle\":\"Almost done!\",\"headerDescription\":\"Please check your inbox for a sign-in link. Follow the link in the email message to be automatically signed in. Don't see the email? Be sure to check your spam folder.\",\"showProfessionalLogin\":false,\"showTermsAndPolicy\":false},\"show_custom_html\":false,\"containerName\":\"context_aware_web\",\"canSkipAddPassword\":false,\"buttonsDisplayOrder\":[{\"key\":\"continue\",\"text\":\"Continue\"},{\"key\":\"google\",\"text\":\"Continue with Google\"},{\"key\":\"facebook\",\"text\":\"Continue with Facebook\"},{\"key\":\"apple\",\"text\":\"Continue with Apple\"},{\"key\":\"emailMe\",\"text\":\"Email Me a Link\"}]}"}, {"id": "22025632851", "value": "{\"landingPage\":{\"headerTitle\":\"Thanks for entering!\",\"headerDescription\":\"Don\u2019t forget to create a Realtor.com\u00ae account so you\u2019re the first to see when rentals you\u2019ll love hit the market.\",\"showProfessionalLogin\":false,\"showTermsAndPolicy\":true,\"showEmailMeLinkBtn\":false},\"passwordPage\":{\"signUp\":{\"headerTitle\":\"Recent Search Successfully Saved!!\",\"headerDescription\":\"Set a password to access your account on all your devices.\",\"showProfessionalLogin\":false,\"showTermsAndPolicy\":false,\"showEmailMeLinkBtn\":false},\"signIn\":{\"headerTitle\":\"Welcome back!\",\"headerDescription\":\"Please enter the password associated with {{email}} to continue.\",\"showProfessionalLogin\":false,\"showTermsAndPolicy\":false,\"showEmailMeLinkBtn\":false},\"WelcomeBack\":{\"headerTitle\":\"Welcome back!\",\"headerDescription\":\"We notice you haven't added the password yet. You'll need one to continue.\",\"showProfessionalLogin\":false,\"showTermsAndPolicy\":false,\"showEmailMeLinkBtn\":false}},\"marketingOptIn\":{\"headerTitle\":\"Thanks for signing up with realtor.com\",\"headerDescription\":\"Stay up to date with the latest tips, news, and insights on the real estate market.\",\"showProfessionalLogin\":false,\"showTermsAndPolicy\":false},\"forgotPassword\":{\"headerTitle\":\"Forgot Password?\",\"headerDescription\":\"No problem! We'll send an email with a link to reset your password.\",\"showProfessionalLogin\":false,\"showTermsAndPolicy\":false},\"almostDone\":{\"headerTitle\":\"Almost done!\",\"headerDescription\":\"Please check your inbox for password reset instructions. Don't see the email? Be sure to check your spam folder.\",\"showProfessionalLogin\":false,\"showTermsAndPolicy\":false},\"emailMeLink\":{\"headerTitle\":\"Email me a Link\",\"headerDescription\":\"Enter your email address and we will send you a link. Follow the link to sign in automatically.\",\"showProfessionalLogin\":false,\"showTermsAndPolicy\":false},\"almostDoneEmailMe\":{\"headerTitle\":\"Almost done!\",\"headerDescription\":\"Please check your inbox for a sign-in link. Follow the link in the email message to be automatically signed in. Don't see the email? Be sure to check your spam folder.\",\"showProfessionalLogin\":false,\"showTermsAndPolicy\":false},\"show_custom_html\":false,\"containerName\":\"context_aware_web\",\"canSkipAddPassword\":true,\"buttonsDisplayOrder\":[{\"key\":\"continue\",\"text\":\"Continue\"},{\"key\":\"google\",\"text\":\"Continue with Google\"},{\"key\":\"facebook\",\"text\":\"Continue with Facebook\"},{\"key\":\"apple\",\"text\":\"Continue with Apple\"}]}"}, {"id": "20618050263", "value": "{\"landingPage\":{\"headerTitle\":\"Log in or create an account to save the search\",\"headerDescription\":\"Save your favorite search and enjoy it from anywhere, on any of your devices.\",\"showProfessionalLogin\":false,\"showTermsAndPolicy\":true,\"showEmailMeLinkBtn\":true},\"passwordPage\":{\"signUp\":{\"headerTitle\":\"Add a password\",\"headerDescription\":\"Set a password to access your account on all your devices.\",\"showProfessionalLogin\":false,\"showTermsAndPolicy\":false,\"showEmailMeLinkBtn\":true},\"signIn\":{\"headerTitle\":\"Welcome back!\",\"headerDescription\":\"Please enter the password associated with {{email}} to continue.\",\"showProfessionalLogin\":false,\"showTermsAndPolicy\":false,\"showEmailMeLinkBtn\":true},\"WelcomeBack\":{\"headerTitle\":\"Welcome back!\",\"headerDescription\":\"We notice you haven't added the password yet.You'll need one to continue.\",\"showProfessionalLogin\":false,\"showTermsAndPolicy\":false,\"showEmailMeLinkBtn\":true}},\"marketingOptIn\":{\"headerTitle\":\"Thanks for signing up with realtor.com\",\"headerDescription\":\"Stay up to date with the latest tips, news, and insights on the real estate market.\",\"showProfessionalLogin\":false,\"showTermsAndPolicy\":false},\"forgotPassword\":{\"headerTitle\":\"Forgot Password?\",\"headerDescription\":\"No problem! We'll send an email with a link to reset your password.\",\"showProfessionalLogin\":false,\"showTermsAndPolicy\":false},\"almostDone\":{\"headerTitle\":\"Almost done!\",\"headerDescription\":\"Please check your inbox for password reset instructions.Don't see the email? Be sure to check your spam folder.\",\"showProfessionalLogin\":false,\"showTermsAndPolicy\":false},\"emailMeLink\":{\"headerTitle\":\"Email Me a Link\",\"headerDescription\":\"Enter your email address and we will send you a link. Follow the link to sign in automatically.\",\"showProfessionalLogin\":false,\"showTermsAndPolicy\":false},\"almostDoneEmailMe\":{\"headerTitle\":\"Almost done!\",\"headerDescription\":\"Please check your inbox for a sign-in link. Follow the link in the email message to be automatically signed in. Don't see the email? Be sure to check your spam folder.\",\"showProfessionalLogin\":false,\"showTermsAndPolicy\":false},\"show_custom_html\":false,\"containerName\":\"context_aware_web\",\"canSkipAddPassword\":true,\"buttonsDisplayOrder\":[{\"key\":\"continue\",\"text\":\"Continue\"},{\"key\":\"google\",\"text\":\"Continue with Google\"},{\"key\":\"facebook\",\"text\":\"Continue with Facebook\"},{\"key\":\"apple\",\"text\":\"Continue with Apple\"},{\"key\":\"emailMe\",\"text\":\"Email Me a Link\"}]}"}, {"id": "21904511441", "value": "{\"landingPage\":{\"headerTitle\":\"Join the smart searchers\",\"headerDescription\":\"Thousands registered for a Realtor.com account  last month and made their home search easier.You can, too!\",\"showProfessionalLogin\":true,\"showTermsAndPolicy\":true,\"showEmailMeLinkBtn\":true},\"passwordPage\":{\"signUp\":{\"headerTitle\":\"Add a password\",\"headerDescription\":\"Set a password to access your account on all your devices.\",\"showProfessionalLogin\":false,\"showTermsAndPolicy\":false,\"showEmailMeLinkBtn\":true},\"signIn\":{\"headerTitle\":\"Welcome back!\",\"headerDescription\":\"Please enter the password associated with {{email}} to continue.\",\"showProfessionalLogin\":false,\"showTermsAndPolicy\":false,\"showEmailMeLinkBtn\":true},\"WelcomeBack\":{\"headerTitle\":\"Welcome back!\",\"headerDescription\":\"We notice you haven't added the password yet.You'll need one to continue.\",\"showProfessionalLogin\":false,\"showTermsAndPolicy\":false,\"showEmailMeLinkBtn\":true}},\"marketingOptIn\":{\"headerTitle\":\"Thanks for signing up with realtor.com\",\"headerDescription\":\"Stay up to date with the latest tips, news, and insights on the real estate market.\",\"showProfessionalLogin\":false,\"showTermsAndPolicy\":false},\"forgotPassword\":{\"headerTitle\":\"Forgot Password?\",\"headerDescription\":\"No problem! We'll send an email with a link to reset your password.\",\"showProfessionalLogin\":false,\"showTermsAndPolicy\":false},\"almostDone\":{\"headerTitle\":\"Almost done!\",\"headerDescription\":\"Please check your inbox for password reset instructions. Don't see the email? Be sure to check your spam folder.\",\"showProfessionalLogin\":false,\"showTermsAndPolicy\":false},\"emailMeLink\":{\"headerTitle\":\"Email Me a Link\",\"headerDescription\":\"Enter your email address and we will send you a link. Follow the link to sign in automatically.\",\"showProfessionalLogin\":false,\"showTermsAndPolicy\":false},\"almostDoneEmailMe\":{\"headerTitle\":\"Almost done!\",\"headerDescription\":\"Please check your inbox for a sign-in link. Follow the link in the email message to be automatically signed in. Don't see the email? Be sure to check your spam folder.\",\"showProfessionalLogin\":false,\"showTermsAndPolicy\":false},\"show_custom_html\":false,\"containerName\":\"context_aware_web\",\"canSkipAddPassword\":false,\"buttonsDisplayOrder\":[{\"key\":\"continue\",\"text\":\"Continue\"},{\"key\":\"google\",\"text\":\"Continue with Google\"},{\"key\":\"facebook\",\"text\":\"Continue with Facebook\"},{\"key\":\"apple\",\"text\":\"Continue with Apple\"},{\"key\":\"emailMe\",\"text\":\"Email Me a Link\"}]}"}, {"id": "20622850167", "value": "{\"landingPage\":{\"headerTitle\":\"Log in or create an account to claim your home\",\"headerDescription\":\"With accurate home details, get regular updates on its true value and monitor the local market.\",\"showProfessionalLogin\":false,\"showTermsAndPolicy\":true,\"showEmailMeLinkBtn\":true},\"passwordPage\":{\"signUp\":{\"headerTitle\":\"Add a password\",\"headerDescription\":\"Set a password to access your account on all your devices.\",\"showProfessionalLogin\":false,\"showTermsAndPolicy\":false,\"showEmailMeLinkBtn\":true},\"signIn\":{\"headerTitle\":\"Welcome back!\",\"headerDescription\":\"Please enter the password associated with {{email}} to continue.\",\"showProfessionalLogin\":false,\"showTermsAndPolicy\":false,\"showEmailMeLinkBtn\":true},\"WelcomeBack\":{\"headerTitle\":\"Welcome back!\",\"headerDescription\":\"We notice you haven't added the password yet.You'll need one to continue.\",\"showProfessionalLogin\":false,\"showTermsAndPolicy\":false,\"showEmailMeLinkBtn\":true}},\"marketingOptIn\":{\"headerTitle\":\"Thanks for signing up with realtor.com\",\"headerDescription\":\"Stay up to date with the latest tips, news, and insights on the real estate market.\",\"showProfessionalLogin\":false,\"showTermsAndPolicy\":false},\"forgotPassword\":{\"headerTitle\":\"Forgot Password?\",\"headerDescription\":\"No problem! We'll send an email with a link to reset your password.\",\"showProfessionalLogin\":false,\"showTermsAndPolicy\":false},\"almostDone\":{\"headerTitle\":\"Almost done!\",\"headerDescription\":\"Please check your inbox for password reset instructions.Don't see the email? Be sure to check your spam folder.\",\"showProfessionalLogin\":false,\"showTermsAndPolicy\":false},\"emailMeLink\":{\"headerTitle\":\"Email Me a Link\",\"headerDescription\":\"Enter your email address and we will send you a link. Follow the link to sign in automatically.\",\"showProfessionalLogin\":false,\"showTermsAndPolicy\":false},\"almostDoneEmailMe\":{\"headerTitle\":\"Almost done!\",\"headerDescription\":\"Please check your inbox for a sign-in link. Follow the link in the email message to be automatically signed in. Don't see the email? Be sure to check your spam folder.\",\"showProfessionalLogin\":false,\"showTermsAndPolicy\":false},\"show_custom_html\":true,\"containerName\":\"context_aware_web\",\"canSkipAddPassword\":false,\"buttonsDisplayOrder\":[{\"key\":\"continue\",\"text\":\"Continue\"},{\"key\":\"google\",\"text\":\"Continue with Google\"},{\"key\":\"facebook\",\"text\":\"Continue with Facebook\"},{\"key\":\"apple\",\"text\":\"Continue with Apple\"},{\"key\":\"emailMe\",\"text\":\"Email Me a Link\"}]}"}, {"id": "21142460348", "value": "{\"landingPage\":{\"headerTitle\":\"Know more about the unique homes being shared all over the web\",\"headerDescription\":\"\",\"showProfessionalLogin\":true,\"showTermsAndPolicy\":true,\"showEmailMeLinkBtn\":true},\"passwordPage\":{\"signUp\":{\"headerTitle\":\"Add a password\",\"headerDescription\":\"Set a password to access your account on all your devices.\",\"showProfessionalLogin\":false,\"showTermsAndPolicy\":false,\"showEmailMeLinkBtn\":true},\"signIn\":{\"headerTitle\":\"Welcome back!\",\"headerDescription\":\"Please enter the password associated with {{email}} to continue.\",\"showProfessionalLogin\":false,\"showTermsAndPolicy\":false,\"showEmailMeLinkBtn\":true},\"WelcomeBack\":{\"headerTitle\":\"Welcome back!\",\"headerDescription\":\"We notice you haven't added the password yet.You'll need one to continue.\",\"showProfessionalLogin\":false,\"showTermsAndPolicy\":false,\"showEmailMeLinkBtn\":true}},\"marketingOptIn\":{\"headerTitle\":\"Thanks for signing up with realtor.com\",\"headerDescription\":\"Stay up to date with the latest tips, news, and insights on the real estate market.\",\"showProfessionalLogin\":false,\"showTermsAndPolicy\":false},\"forgotPassword\":{\"headerTitle\":\"Forgot Password?\",\"headerDescription\":\"No problem! We'll send an email with a link to reset your password.\",\"showProfessionalLogin\":false,\"showTermsAndPolicy\":false},\"almostDone\":{\"headerTitle\":\"Almost done!\",\"headerDescription\":\"Please check your inbox for password reset instructions. Don't see the email? Be sure to check your spam folder.\",\"showProfessionalLogin\":false,\"showTermsAndPolicy\":false},\"emailMeLink\":{\"headerTitle\":\"Email Me a Link\",\"headerDescription\":\"Enter your email address and we will send you a link. Follow the link to sign in automatically.\",\"showProfessionalLogin\":false,\"showTermsAndPolicy\":false},\"almostDoneEmailMe\":{\"headerTitle\":\"Almost done!\",\"headerDescription\":\"Please check your inbox for a sign-in link. Follow the link in the email message to be automatically signed in. Don't see the email? Be sure to check your spam folder.\",\"showProfessionalLogin\":false,\"showTermsAndPolicy\":false},\"show_custom_html\":false,\"containerName\":\"context_aware_web\",\"canSkipAddPassword\":false,\"buttonsDisplayOrder\":[{\"key\":\"continue\",\"text\":\"Continue\"},{\"key\":\"google\",\"text\":\"Continue with Google\"},{\"key\":\"facebook\",\"text\":\"Continue with Facebook\"},{\"key\":\"apple\",\"text\":\"Continue with Apple\"},{\"key\":\"emailMe\",\"text\":\"Email Me a Link\"}]}"}, {"id": "20691220938", "value": "{\"landingPage\":{\"headerTitle\":\"Log in or create an account to collaborate!\",\"headerDescription\":\"Collaboration on Realtor.com requires a free account.\",\"showProfessionalLogin\":false,\"showTermsAndPolicy\":true,\"showEmailMeLinkBtn\":true},\"passwordPage\":{\"signUp\":{\"headerTitle\":\"Add a password\",\"headerDescription\":\"Set a password to access your account on all your devices.\",\"showProfessionalLogin\":false,\"showTermsAndPolicy\":false,\"showEmailMeLinkBtn\":true},\"signIn\":{\"headerTitle\":\"Welcome back!\",\"headerDescription\":\"Please enter the password associated with {{email}} to continue.\",\"showProfessionalLogin\":false,\"showTermsAndPolicy\":false,\"showEmailMeLinkBtn\":true},\"WelcomeBack\":{\"headerTitle\":\"Welcome back!\",\"headerDescription\":\"We notice you haven't added the password yet.You'll need one to continue.\",\"showProfessionalLogin\":false,\"showTermsAndPolicy\":false,\"showEmailMeLinkBtn\":true}},\"marketingOptIn\":{\"headerTitle\":\"Thanks for signing up with realtor.com\",\"headerDescription\":\"Stay up to date with the latest tips, news, and insights on the real estate market.\",\"showProfessionalLogin\":false,\"showTermsAndPolicy\":false},\"forgotPassword\":{\"headerTitle\":\"Forgot Password?\",\"headerDescription\":\"No problem! We'll send an email with a link to reset your password.\",\"showProfessionalLogin\":false,\"showTermsAndPolicy\":false},\"almostDone\":{\"headerTitle\":\"Almost done!\",\"headerDescription\":\"Please check your inbox for password reset instructions.Don't see the email? Be sure to check your spam folder.\",\"showProfessionalLogin\":false,\"showTermsAndPolicy\":false},\"emailMeLink\":{\"headerTitle\":\"Email Me a Link\",\"headerDescription\":\"Enter your email address and we will send you a link. Follow the link to sign in automatically.\",\"showProfessionalLogin\":false,\"showTermsAndPolicy\":false},\"almostDoneEmailMe\":{\"headerTitle\":\"Almost done!\",\"headerDescription\":\"Please check your inbox for a sign-in link. Follow the link in the email message to be automatically signed in. Don't see the email? Be sure to check your spam folder.\",\"showProfessionalLogin\":false,\"showTermsAndPolicy\":false},\"show_custom_html\":false,\"containerName\":\"context_aware_web\",\"canSkipAddPassword\":false,\"buttonsDisplayOrder\":[{\"key\":\"continue\",\"text\":\"Continue\"},{\"key\":\"google\",\"text\":\"Continue with Google\"},{\"key\":\"facebook\",\"text\":\"Continue with Facebook\"},{\"key\":\"apple\",\"text\":\"Continue with Apple\"},{\"key\":\"emailMe\",\"text\":\"Email Me a Link\"}]}"}, {"id": "20647400094", "value": "{\"landingPage\":{\"headerTitle\":\"Log in or create an account to save your favorite homes\",\"headerDescription\":\"Save your favorite home and enjoy it from anywhere, on any of your devices.\",\"showProfessionalLogin\":false,\"showTermsAndPolicy\":true,\"showEmailMeLinkBtn\":true},\"passwordPage\":{\"signUp\":{\"headerTitle\":\"Add a password\",\"headerDescription\":\"Set a password to access your account on all your devices.\",\"showProfessionalLogin\":false,\"showTermsAndPolicy\":false,\"showEmailMeLinkBtn\":true},\"signIn\":{\"headerTitle\":\"Welcome back!\",\"headerDescription\":\"Please enter the password associated with {{email}} to continue.\",\"showProfessionalLogin\":false,\"showTermsAndPolicy\":false,\"showEmailMeLinkBtn\":true},\"WelcomeBack\":{\"headerTitle\":\"Welcome back!\",\"headerDescription\":\"We notice you haven't added the password yet.You'll need one to continue.\",\"showProfessionalLogin\":false,\"showTermsAndPolicy\":false,\"showEmailMeLinkBtn\":true}},\"marketingOptIn\":{\"headerTitle\":\"Thanks for signing up with realtor.com\",\"headerDescription\":\"Stay up to date with the latest tips, news, and insights on the real estate market.\",\"showProfessionalLogin\":false,\"showTermsAndPolicy\":false},\"forgotPassword\":{\"headerTitle\":\"Forgot Password?\",\"headerDescription\":\"No problem! We'll send an email with a link to reset your password.\",\"showProfessionalLogin\":false,\"showTermsAndPolicy\":false},\"almostDone\":{\"headerTitle\":\"Almost done!\",\"headerDescription\":\"Please check your inbox for password reset instructions.Don't see the email? Be sure to check your spam folder.\",\"showProfessionalLogin\":false,\"showTermsAndPolicy\":false},\"emailMeLink\":{\"headerTitle\":\"Email Me a Link\",\"headerDescription\":\"Enter your email address and we will send you a link. Follow the link to sign in automatically.\",\"showProfessionalLogin\":false,\"showTermsAndPolicy\":false},\"almostDoneEmailMe\":{\"headerTitle\":\"Almost done!\",\"headerDescription\":\"Please check your inbox for a sign-in link. Follow the link in the email message to be automatically signed in. Don't see the email? Be sure to check your spam folder.\",\"showProfessionalLogin\":false,\"showTermsAndPolicy\":false},\"show_custom_html\":false,\"containerName\":\"context_aware_web\",\"canSkipAddPassword\":true,\"buttonsDisplayOrder\":[{\"key\":\"continue\",\"text\":\"Continue\"},{\"key\":\"google\",\"text\":\"Continue with Google\"},{\"key\":\"facebook\",\"text\":\"Continue with Facebook\"},{\"key\":\"apple\",\"text\":\"Continue with Apple\"},{\"key\":\"emailMe\",\"text\":\"Email Me a Link\"}]}"}, {"id": "21275920011", "value": "{\"landingPage\":{\"headerTitle\":\"Log in or create an account to claim your home\",\"headerDescription\":\"Get updates on your home value and equity changes.\",\"showProfessionalLogin\":false,\"showTermsAndPolicy\":true,\"showEmailMeLinkBtn\":true},\"passwordPage\":{\"signUp\":{\"headerTitle\":\"Add a password\",\"headerDescription\":\"Set a password to access your account on all your devices.\",\"showProfessionalLogin\":false,\"showTermsAndPolicy\":false,\"showEmailMeLinkBtn\":true},\"signIn\":{\"headerTitle\":\"Welcome back!\",\"headerDescription\":\"Please enter the password associated with {{email}} to continue.\",\"showProfessionalLogin\":false,\"showTermsAndPolicy\":false,\"showEmailMeLinkBtn\":true},\"WelcomeBack\":{\"headerTitle\":\"Welcome back!\",\"headerDescription\":\"We notice you haven't added the password yet.You'll need one to continue.\",\"showProfessionalLogin\":false,\"showTermsAndPolicy\":false,\"showEmailMeLinkBtn\":true}},\"marketingOptIn\":{\"headerTitle\":\"Thanks for signing up with realtor.com\",\"headerDescription\":\"Stay up to date with the latest tips, news, and insights on the real estate market.\",\"showProfessionalLogin\":false,\"showTermsAndPolicy\":false},\"forgotPassword\":{\"headerTitle\":\"Forgot Password?\",\"headerDescription\":\"No problem! We'll send an email with a link to reset your password.\",\"showProfessionalLogin\":false,\"showTermsAndPolicy\":false},\"almostDone\":{\"headerTitle\":\"Almost done!\",\"headerDescription\":\"Please check your inbox for password reset instructions.Don't see the email? Be sure to check your spam folder.\",\"showProfessionalLogin\":false,\"showTermsAndPolicy\":false},\"emailMeLink\":{\"headerTitle\":\"Email Me a Link\",\"headerDescription\":\"Enter your email address and we will send you a link. Follow the link to sign in automatically.\",\"showProfessionalLogin\":false,\"showTermsAndPolicy\":false},\"almostDoneEmailMe\":{\"headerTitle\":\"Almost done!\",\"headerDescription\":\"Please check your inbox for a sign-in link. Follow the link in the email message to be automatically signed in. Don't see the email? Be sure to check your spam folder.\",\"showProfessionalLogin\":false,\"showTermsAndPolicy\":false},\"show_custom_html\":true,\"containerName\":\"context_aware_web\",\"canSkipAddPassword\":false,\"buttonsDisplayOrder\":[{\"key\":\"continue\",\"text\":\"Continue\"},{\"key\":\"google\",\"text\":\"Continue with Google\"},{\"key\":\"facebook\",\"text\":\"Continue with Facebook\"},{\"key\":\"apple\",\"text\":\"Continue with Apple\"},{\"key\":\"emailMe\",\"text\":\"Email Me a Link\"}]}"}, {"id": "21134900381", "value": "{\"landingPage\":{\"headerTitle\":\"We follow the housing market. Let us keep you informed.\",\"headerDescription\":\"Login or create a free account.\",\"showProfessionalLogin\":true,\"showTermsAndPolicy\":true,\"showEmailMeLinkBtn\":true},\"passwordPage\":{\"signUp\":{\"headerTitle\":\"Add a password\",\"headerDescription\":\"Set a password to access your account on all your devices.\",\"showProfessionalLogin\":false,\"showTermsAndPolicy\":false,\"showEmailMeLinkBtn\":true},\"signIn\":{\"headerTitle\":\"Welcome back!\",\"headerDescription\":\"Please enter the password associated with {{email}} to continue.\",\"showProfessionalLogin\":false,\"showTermsAndPolicy\":false,\"showEmailMeLinkBtn\":true},\"WelcomeBack\":{\"headerTitle\":\"Welcome back!\",\"headerDescription\":\"We notice you haven't added the password yet.You'll need one to continue.\",\"showProfessionalLogin\":false,\"showTermsAndPolicy\":false,\"showEmailMeLinkBtn\":true}},\"marketingOptIn\":{\"headerTitle\":\"Thanks for signing up with realtor.com\",\"headerDescription\":\"Stay up to date with the latest tips, news, and insights on the real estate market.\",\"showProfessionalLogin\":false,\"showTermsAndPolicy\":false},\"forgotPassword\":{\"headerTitle\":\"Forgot Password?\",\"headerDescription\":\"No problem! We'll send an email with a link to reset your password.\",\"showProfessionalLogin\":false,\"showTermsAndPolicy\":false},\"almostDone\":{\"headerTitle\":\"Almost done!\",\"headerDescription\":\"Please check your inbox for password reset instructions. Don't see the email? Be sure to check your spam folder.\",\"showProfessionalLogin\":false,\"showTermsAndPolicy\":false},\"emailMeLink\":{\"headerTitle\":\"Email Me a Link\",\"headerDescription\":\"Enter your email address and we will send you a link. Follow the link to sign in automatically.\",\"showProfessionalLogin\":false,\"showTermsAndPolicy\":false},\"almostDoneEmailMe\":{\"headerTitle\":\"Almost done!\",\"headerDescription\":\"Please check your inbox for a sign-in link. Follow the link in the email message to be automatically signed in. Don't see the email? Be sure to check your spam folder.\",\"showProfessionalLogin\":false,\"showTermsAndPolicy\":false},\"show_custom_html\":false,\"containerName\":\"context_aware_web\",\"canSkipAddPassword\":false,\"buttonsDisplayOrder\":[{\"key\":\"continue\",\"text\":\"Continue\"},{\"key\":\"google\",\"text\":\"Continue with Google\"},{\"key\":\"facebook\",\"text\":\"Continue with Facebook\"},{\"key\":\"apple\",\"text\":\"Continue with Apple\"},{\"key\":\"emailMe\",\"text\":\"Email Me a Link\"}]}"}, {"id": "20520622729", "value": "{\"landingPage\":{\"headerTitle\":\"Log in or create an account\",\"headerDescription\":\"\",\"showProfessionalLogin\":true,\"showTermsAndPolicy\":true,\"showEmailMeLinkBtn\":true},\"passwordPage\":{\"signUp\":{\"headerTitle\":\"Add a password\",\"headerDescription\":\"Set a password to access your account on all your devices.\",\"showProfessionalLogin\":false,\"showTermsAndPolicy\":false,\"showEmailMeLinkBtn\":true},\"signIn\":{\"headerTitle\":\"Welcome back!\",\"headerDescription\":\"Please enter the password associated with {{email}} to continue.\",\"showProfessionalLogin\":false,\"showTermsAndPolicy\":false,\"showEmailMeLinkBtn\":true},\"WelcomeBack\":{\"headerTitle\":\"Welcome back!\",\"headerDescription\":\"We notice you haven't added the password yet. You'll need one to continue.\",\"showProfessionalLogin\":false,\"showTermsAndPolicy\":false,\"showEmailMeLinkBtn\":true}},\"success\":{\"signUp\":{\"headerTitle\":\"Sign-up successful!\",\"headerDescription\":\"You now have access to more from Realtor.com!\",\"show\":true,\"dynamicHtml\":\"<html><head></head><body><div><a href=\\\"https://www.realtor.com/sell/sellers-marketplace\\\"><img src=\\\"https://d32kodjovuzxj9.cloudfront.net/images/img-selloptions.svg\\\"alt = \\\"Seller Marketplace\\\" width=\\\"300\\\" height=\\\"200\\\"></a></div><div style=\\\"width: 100%; text-align: center;\\\">Do you have a home to sell? If so, check out our <a href=\\\"https://www.realtor.com/sell/sellers-marketplace\\\">Seller's Marketplace</a>.</li></div><div style=\\\"width: 100%; height: 15px; border-bottom: 1px solid black; text-align: center; margin: 10px 0px 24px;\\\"><span style=\\\"font-size: 14px; background-color: rgb(255, 255, 255); padding: 4px 10px 0px; display: inline-block; margin: 0px;\\\">or</span></div></body></html>\"},\"signIn\":{\"headerTitle\":\"Sign-in successful!\",\"show\":true,\"headerDescription\":\"You now have access to more from Realtor.com!\",\"dynamicHtml\":\"<html><head></head><body><div><a href=\\\"https://www.realtor.com/sell/sellers-marketplace\\\"><img src=\\\"https://d32kodjovuzxj9.cloudfront.net/images/img-selloptions.svg\\\"alt = \\\"Seller Marketplace\\\" width=\\\"300\\\" height=\\\"200\\\"></a></div><div style=\\\"width: 100%; text-align: center;\\\">Do you have a home to sell? If so, check out our <a href=\\\"https://www.realtor.com/sell/sellers-marketplace\\\">Seller's Marketplace</a>.</li></div><div style=\\\"width: 100%; height: 15px; border-bottom: 1px solid black; text-align: center; margin: 10px 0px 24px;\\\"><span style=\\\"font-size: 14px; background-color: rgb(255, 255, 255); padding: 4px 10px 0px; display: inline-block; margin: 0px;\\\">or</span></div></body></html>\"}},\"marketingOptIn\":{\"headerTitle\":\"Thanks for signing up with realtor.com\",\"headerDescription\":\"Stay up to date with the latest tips, news, and insights on the real estate market.\",\"showProfessionalLogin\":false,\"showTermsAndPolicy\":false},\"forgotPassword\":{\"headerTitle\":\"Forgot Password?\",\"headerDescription\":\"No problem! We'll send an email with a link to reset your password.\",\"showProfessionalLogin\":false,\"showTermsAndPolicy\":false},\"almostDone\":{\"headerTitle\":\"Almost done!\",\"headerDescription\":\"Please check your inbox for password reset instructions. Don't see the email? Be sure to check your spam folder.\",\"showProfessionalLogin\":false,\"showTermsAndPolicy\":false},\"emailMeLink\":{\"headerTitle\":\"Email Me a Link\",\"headerDescription\":\"Enter your email address and we will send you a link. Follow the link to sign in automatically.\",\"showProfessionalLogin\":false,\"showTermsAndPolicy\":false},\"almostDoneEmailMe\":{\"headerTitle\":\"Almost done!\",\"headerDescription\":\"Please check your inbox for a sign-in link. Follow the link in the email message to be automatically signed in. Don't see the email? Be sure to check your spam folder.\",\"showProfessionalLogin\":false,\"showTermsAndPolicy\":false},\"show_custom_html\":false,\"containerName\":\"context_aware_web\",\"canSkipAddPassword\":false,\"buttonsDisplayOrder\":[{\"key\":\"continue\",\"text\":\"Continue\"},{\"key\":\"google\",\"text\":\"Continue with Google\"},{\"key\":\"facebook\",\"text\":\"Continue with Facebook\"},{\"key\":\"apple\",\"text\":\"Continue with Apple\"},{\"key\":\"emailMe\",\"text\":\"Email Me a Link\"}]}"}, {"id": "20639410267", "value": "{\"landingPage\":{\"headerTitle\":\"Log in or create an account to save the search\",\"headerDescription\":\"Save your favorite search and enjoy it from anywhere, on any of your devices.\",\"showProfessionalLogin\":false,\"showTermsAndPolicy\":true,\"showEmailMeLinkBtn\":true},\"passwordPage\":{\"signUp\":{\"headerTitle\":\"Add a password\",\"headerDescription\":\"Set a password to access your account on all your devices.\",\"showProfessionalLogin\":false,\"showTermsAndPolicy\":false,\"showEmailMeLinkBtn\":true},\"signIn\":{\"headerTitle\":\"Welcome back!\",\"headerDescription\":\"Please enter the password associated with {{email}} to continue.\",\"showProfessionalLogin\":false,\"showTermsAndPolicy\":false,\"showEmailMeLinkBtn\":true},\"WelcomeBack\":{\"headerTitle\":\"Welcome back!\",\"headerDescription\":\"We notice you haven't added the password yet.You'll need one to continue.\",\"showProfessionalLogin\":false,\"showTermsAndPolicy\":false,\"showEmailMeLinkBtn\":true}},\"marketingOptIn\":{\"headerTitle\":\"Thanks for signing up with realtor.com\",\"headerDescription\":\"Stay up to date with the latest tips, news, and insights on the real estate market.\",\"showProfessionalLogin\":false,\"showTermsAndPolicy\":false},\"forgotPassword\":{\"headerTitle\":\"Forgot Password?\",\"headerDescription\":\"No problem! We'll send an email with a link to reset your password.\",\"showProfessionalLogin\":false,\"showTermsAndPolicy\":false},\"almostDone\":{\"headerTitle\":\"Almost done!\",\"headerDescription\":\"Please check your inbox for password reset instructions. Don't see the email? Be sure to check your spam folder.\",\"showProfessionalLogin\":false,\"showTermsAndPolicy\":false},\"emailMeLink\":{\"headerTitle\":\"Email Me a Link\",\"headerDescription\":\"Enter your email address and we will send you a link. Follow the link to sign in automatically.\",\"showProfessionalLogin\":false,\"showTermsAndPolicy\":false},\"almostDoneEmailMe\":{\"headerTitle\":\"Almost done!\",\"headerDescription\":\"Please check your inbox for a sign-in link. Follow the link in the email message to be automatically signed in. Don't see the email? Be sure to check your spam folder.\",\"showProfessionalLogin\":false,\"showTermsAndPolicy\":false},\"show_custom_html\":false,\"containerName\":\"context_aware_web\",\"canSkipAddPassword\":true,\"buttonsDisplayOrder\":[{\"key\":\"continue\",\"text\":\"Continue\"},{\"key\":\"google\",\"text\":\"Continue with Google\"},{\"key\":\"facebook\",\"text\":\"Continue with Facebook\"},{\"key\":\"apple\",\"text\":\"Continue with Apple\"},{\"key\":\"emailMe\",\"text\":\"Email Me a Link\"}]}"}, {"id": "21268770003", "value": "{\"landingPage\":{\"headerTitle\":\"Log in or create an account to claim your home\",\"headerDescription\":\"Claim home to edit your home details and remove photos.\",\"showProfessionalLogin\":false,\"showTermsAndPolicy\":true,\"showEmailMeLinkBtn\":true},\"passwordPage\":{\"signUp\":{\"headerTitle\":\"Add a password\",\"headerDescription\":\"Set a password to access your account on all your devices.\",\"showProfessionalLogin\":false,\"showTermsAndPolicy\":false,\"showEmailMeLinkBtn\":true},\"signIn\":{\"headerTitle\":\"Welcome back!\",\"headerDescription\":\"Please enter the password associated with {{email}} to continue.\",\"showProfessionalLogin\":false,\"showTermsAndPolicy\":false,\"showEmailMeLinkBtn\":true},\"WelcomeBack\":{\"headerTitle\":\"Welcome back!\",\"headerDescription\":\"We notice you haven't added the password yet.You'll need one to continue.\",\"showProfessionalLogin\":false,\"showTermsAndPolicy\":false,\"showEmailMeLinkBtn\":true}},\"marketingOptIn\":{\"headerTitle\":\"Thanks for signing up with realtor.com\",\"headerDescription\":\"Stay up to date with the latest tips, news, and insights on the real estate market.\",\"showProfessionalLogin\":false,\"showTermsAndPolicy\":false},\"forgotPassword\":{\"headerTitle\":\"Forgot Password?\",\"headerDescription\":\"No problem! We'll send an email with a link to reset your password.\",\"showProfessionalLogin\":false,\"showTermsAndPolicy\":false},\"almostDone\":{\"headerTitle\":\"Almost done!\",\"headerDescription\":\"Please check your inbox for password reset instructions.Don't see the email? Be sure to check your spam folder.\",\"showProfessionalLogin\":false,\"showTermsAndPolicy\":false},\"emailMeLink\":{\"headerTitle\":\"Email Me a Link\",\"headerDescription\":\"Enter your email address and we will send you a link. Follow the link to sign in automatically.\",\"showProfessionalLogin\":false,\"showTermsAndPolicy\":false},\"almostDoneEmailMe\":{\"headerTitle\":\"Almost done!\",\"headerDescription\":\"Please check your inbox for a sign-in link. Follow the link in the email message to be automatically signed in. Don't see the email? Be sure to check your spam folder.\",\"showProfessionalLogin\":false,\"showTermsAndPolicy\":false},\"show_custom_html\":true,\"containerName\":\"context_aware_web\",\"canSkipAddPassword\":false,\"buttonsDisplayOrder\":[{\"key\":\"continue\",\"text\":\"Continue\"},{\"key\":\"google\",\"text\":\"Continue with Google\"},{\"key\":\"facebook\",\"text\":\"Continue with Facebook\"},{\"key\":\"apple\",\"text\":\"Continue with Apple\"},{\"key\":\"emailMe\",\"text\":\"Email Me a Link\"}]}"}, {"id": "20628270213", "value": "{\"landingPage\":{\"headerTitle\":\"Login or create an account to attend this event\",\"headerDescription\":\"Schedule your Live Open House event and enjoy it from anywhere on any of your devices.\",\"showProfessionalLogin\":false,\"showTermsAndPolicy\":true,\"showEmailMeLinkBtn\":true},\"passwordPage\":{\"signUp\":{\"headerTitle\":\"Add a password\",\"headerDescription\":\"Set a password to access your account on all your devices.\",\"showProfessionalLogin\":false,\"showTermsAndPolicy\":false,\"showEmailMeLinkBtn\":true},\"signIn\":{\"headerTitle\":\"Welcome back!\",\"headerDescription\":\"Please enter the password associated with {{email}} to continue.\",\"showProfessionalLogin\":false,\"showTermsAndPolicy\":false,\"showEmailMeLinkBtn\":true},\"WelcomeBack\":{\"headerTitle\":\"Welcome back!\",\"headerDescription\":\"We notice you haven't added the password yet.You'll need one to continue.\",\"showProfessionalLogin\":false,\"showTermsAndPolicy\":false,\"showEmailMeLinkBtn\":true}},\"marketingOptIn\":{\"headerTitle\":\"Thanks for signing up with realtor.com\",\"headerDescription\":\"Stay up to date with the latest tips, news, and insights on the real estate market.\",\"showProfessionalLogin\":false,\"showTermsAndPolicy\":false},\"forgotPassword\":{\"headerTitle\":\"Forgot Password?\",\"headerDescription\":\"No problem! We'll send an email with a link to reset your password.\",\"showProfessionalLogin\":false,\"showTermsAndPolicy\":false},\"almostDone\":{\"headerTitle\":\"Almost done!\",\"headerDescription\":\"Please check your inbox for password reset instructions.Don't see the email? Be sure to check your spam folder.\",\"showProfessionalLogin\":false,\"showTermsAndPolicy\":false},\"emailMeLink\":{\"headerTitle\":\"Email Me a Link\",\"headerDescription\":\"Enter your email address and we will send you a link. Follow the link to sign in automatically.\",\"showProfessionalLogin\":false,\"showTermsAndPolicy\":false},\"almostDoneEmailMe\":{\"headerTitle\":\"Almost done!\",\"headerDescription\":\"Please check your inbox for a sign-in link. Follow the link in the email message to be automatically signed in. Don't see the email? Be sure to check your spam folder.\",\"showProfessionalLogin\":false,\"showTermsAndPolicy\":false},\"show_custom_html\":false,\"containerName\":\"context_aware_web\",\"canSkipAddPassword\":true,\"buttonsDisplayOrder\":[{\"key\":\"continue\",\"text\":\"Continue\"},{\"key\":\"google\",\"text\":\"Continue with Google\"},{\"key\":\"facebook\",\"text\":\"Continue with Facebook\"},{\"key\":\"apple\",\"text\":\"Continue with Apple\"},{\"key\":\"emailMe\",\"text\":\"Email Me a Link\"}]}"}, {"id": "20719300839", "value": "{\"landingPage\":{\"headerTitle\":\"Thanks for entering the Realtor.com\u00ae The Addams Family 2 Tickets Sweepstakes!\",\"headerDescription\":\"Let\u2019s stay in touch. Sign up for a Realtor.com account to see when frighteningly good homes hit the market in your area.\",\"showProfessionalLogin\":false,\"showTermsAndPolicy\":true},\"passwordPage\":{\"signUp\":{\"headerTitle\":\"Add a password\",\"headerDescription\":\"Set a password to access your account on all your devices.\",\"showProfessionalLogin\":false,\"showTermsAndPolicy\":false},\"signIn\":{\"headerTitle\":\"Welcome back!\",\"headerDescription\":\"Please enter the password associated with {{email}} to continue.\",\"showProfessionalLogin\":false,\"showTermsAndPolicy\":false},\"WelcomeBack\":{\"headerTitle\":\"Welcome back!\",\"headerDescription\":\"We notice you haven't added the password yet.You'll need one to continue.\",\"showProfessionalLogin\":false,\"showTermsAndPolicy\":false}},\"marketingOptIn\":{\"headerTitle\":\"Thanks for signing up with realtor.com\",\"headerDescription\":\"Stay up to date with the latest tips, news, and insights on the real estate market.\",\"showProfessionalLogin\":false,\"showTermsAndPolicy\":false},\"forgotPassword\":{\"headerTitle\":\"Forgot Password?\",\"headerDescription\":\"No problem! We'll send an email with a link to reset your password.\",\"showProfessionalLogin\":false,\"showTermsAndPolicy\":false},\"almostDone\":{\"headerTitle\":\"Almost done!\",\"headerDescription\":\"Please check your inbox for password reset instructions.Don't see the email? Be sure to check your spam folder.\",\"showProfessionalLogin\":false,\"showTermsAndPolicy\":false},\"show_custom_html\":false,\"containerName\":\"context_aware_web\",\"canSkipAddPassword\":false,\"buttonsDisplayOrder\":[{\"key\":\"continue\",\"text\":\"Continue\"},{\"key\":\"google\",\"text\":\"Continue with Google\"},{\"key\":\"facebook\",\"text\":\"Continue with Facebook\"},{\"key\":\"apple\",\"text\":\"Continue with Apple\"}]}"}, {"id": "21287371349", "value": "{\"landingPage\":{\"headerTitle\":\"Get the latest real estate news and advice straight to your inbox\",\"headerDescription\":\"\",\"showProfessionalLogin\":true,\"showTermsAndPolicy\":true,\"showEmailMeLinkBtn\":true},\"passwordPage\":{\"signUp\":{\"headerTitle\":\"Add a password\",\"headerDescription\":\"Set a password to access your account on all your devices.\",\"showProfessionalLogin\":false,\"showTermsAndPolicy\":false,\"showEmailMeLinkBtn\":true},\"signIn\":{\"headerTitle\":\"Welcome back!\",\"headerDescription\":\"Please enter the password associated with {{email}} to continue.\",\"showProfessionalLogin\":false,\"showTermsAndPolicy\":false,\"showEmailMeLinkBtn\":true},\"WelcomeBack\":{\"headerTitle\":\"Welcome back!\",\"headerDescription\":\"We notice you haven't added the password yet.You'll need one to continue.\",\"showProfessionalLogin\":false,\"showTermsAndPolicy\":false,\"showEmailMeLinkBtn\":true}},\"marketingOptIn\":{\"headerTitle\":\"Thanks for signing up with realtor.com\",\"headerDescription\":\"Stay up to date with the latest tips, news, and insights on the real estate market.\",\"showProfessionalLogin\":false,\"showTermsAndPolicy\":false},\"forgotPassword\":{\"headerTitle\":\"Forgot Password?\",\"headerDescription\":\"No problem! We'll send an email with a link to reset your password.\",\"showProfessionalLogin\":false,\"showTermsAndPolicy\":false},\"almostDone\":{\"headerTitle\":\"Almost done!\",\"headerDescription\":\"Please check your inbox for password reset instructions. Don't see the email? Be sure to check your spam folder.\",\"showProfessionalLogin\":false,\"showTermsAndPolicy\":false},\"emailMeLink\":{\"headerTitle\":\"Email Me a Link\",\"headerDescription\":\"Enter your email address and we will send you a link. Follow the link to sign in automatically.\",\"showProfessionalLogin\":false,\"showTermsAndPolicy\":false},\"almostDoneEmailMe\":{\"headerTitle\":\"Almost done!\",\"headerDescription\":\"Please check your inbox for a sign-in link. Follow the link in the email message to be automatically signed in. Don't see the email? Be sure to check your spam folder.\",\"showProfessionalLogin\":false,\"showTermsAndPolicy\":false},\"show_custom_html\":false,\"containerName\":\"context_aware_web\",\"canSkipAddPassword\":false,\"buttonsDisplayOrder\":[{\"key\":\"continue\",\"text\":\"Continue\"},{\"key\":\"google\",\"text\":\"Continue with Google\"},{\"key\":\"facebook\",\"text\":\"Continue with Facebook\"},{\"key\":\"apple\",\"text\":\"Continue with Apple\"},{\"key\":\"emailMe\",\"text\":\"Email Me a Link\"}]}"}, {"id": "21179472018", "value": "{\"landingPage\":{\"headerTitle\":\"Get more out of Realtor.com with a free account!\",\"headerDescription\":\"When you sign up for an account, we can send you the best home recommendations for you as soon as they hit the market.\",\"showProfessionalLogin\":true,\"showTermsAndPolicy\":true,\"showEmailMeLinkBtn\":true},\"passwordPage\":{\"signUp\":{\"headerTitle\":\"Add a password\",\"headerDescription\":\"Set a password to access your account on all your devices.\",\"showProfessionalLogin\":false,\"showTermsAndPolicy\":false,\"showEmailMeLinkBtn\":true},\"signIn\":{\"headerTitle\":\"Welcome back!\",\"headerDescription\":\"Please enter the password associated with {{email}} to continue.\",\"showProfessionalLogin\":false,\"showTermsAndPolicy\":false,\"showEmailMeLinkBtn\":true},\"WelcomeBack\":{\"headerTitle\":\"Welcome back!\",\"headerDescription\":\"We notice you haven't added the password yet.You'll need one to continue.\",\"showProfessionalLogin\":false,\"showTermsAndPolicy\":false,\"showEmailMeLinkBtn\":true}},\"marketingOptIn\":{\"headerTitle\":\"Thanks for signing up with realtor.com\",\"headerDescription\":\"Stay up to date with the latest tips, news, and insights on the real estate market.\",\"showProfessionalLogin\":false,\"showTermsAndPolicy\":false},\"forgotPassword\":{\"headerTitle\":\"Forgot Password?\",\"headerDescription\":\"No problem! We'll send an email with a link to reset your password.\",\"showProfessionalLogin\":false,\"showTermsAndPolicy\":false},\"almostDone\":{\"headerTitle\":\"Almost done!\",\"headerDescription\":\"Please check your inbox for password reset instructions. Don't see the email? Be sure to check your spam folder.\",\"showProfessionalLogin\":false,\"showTermsAndPolicy\":false},\"emailMeLink\":{\"headerTitle\":\"Email Me a Link\",\"headerDescription\":\"Enter your email address and we will send you a link. Follow the link to sign in automatically.\",\"showProfessionalLogin\":false,\"showTermsAndPolicy\":false},\"almostDoneEmailMe\":{\"headerTitle\":\"Almost done!\",\"headerDescription\":\"Please check your inbox for a sign-in link. Follow the link in the email message to be automatically signed in. Don't see the email? Be sure to check your spam folder.\",\"showProfessionalLogin\":false,\"showTermsAndPolicy\":false},\"show_custom_html\":false,\"containerName\":\"context_aware_web\",\"canSkipAddPassword\":false,\"buttonsDisplayOrder\":[{\"key\":\"continue\",\"text\":\"Continue\"},{\"key\":\"google\",\"text\":\"Continue with Google\"},{\"key\":\"facebook\",\"text\":\"Continue with Facebook\"},{\"key\":\"apple\",\"text\":\"Continue with Apple\"},{\"key\":\"emailMe\",\"text\":\"Email Me a Link\"}]}"}, {"id": "21230332381", "value": "{\"landingPage\":{\"headerTitle\":\"Download our First-time Homebuying 101 ebook for free\",\"headerDescription\":\"Sign in or create an account. Available in English and Spanish.\",\"showProfessionalLogin\":false,\"showTermsAndPolicy\":true},\"passwordPage\":{\"signUp\":{\"headerTitle\":\"Recent Search Successfully Saved!!\",\"headerDescription\":\"Set a password to access your account on all your devices.\",\"showProfessionalLogin\":false,\"showTermsAndPolicy\":false},\"signIn\":{\"headerTitle\":\"Welcome back!\",\"headerDescription\":\"Please enter the password associated with {{email}} to continue.\",\"showProfessionalLogin\":false,\"showTermsAndPolicy\":false},\"WelcomeBack\":{\"headerTitle\":\"Welcome back!\",\"headerDescription\":\"We notice you haven't added the password yet. You'll need one to continue.\",\"showProfessionalLogin\":false,\"showTermsAndPolicy\":false}},\"marketingOptIn\":{\"headerTitle\":\"Thanks for signing up with realtor.com\",\"headerDescription\":\"Stay up to date with the latest tips, news, and insights on the real estate market.\",\"showProfessionalLogin\":false,\"showTermsAndPolicy\":false},\"forgotPassword\":{\"headerTitle\":\"Forgot Password?\",\"headerDescription\":\"No problem! We'll send an email with a link to reset your password.\",\"showProfessionalLogin\":false,\"showTermsAndPolicy\":false},\"almostDone\":{\"headerTitle\":\"Almost done!\",\"headerDescription\":\"Please check your inbox for password reset instructions. Don't see the email? Be sure to check your spam folder.\",\"showProfessionalLogin\":false,\"showTermsAndPolicy\":false},\"show_custom_html\":false,\"containerName\":\"context_aware_web\",\"canSkipAddPassword\":true,\"buttonsDisplayOrder\":[{\"key\":\"continue\",\"text\":\"Continue\"},{\"key\":\"google\",\"text\":\"Continue with Google\"},{\"key\":\"facebook\",\"text\":\"Continue with Facebook\"},{\"key\":\"apple\",\"text\":\"Continue with Apple\"}]}"}, {"id": "21157261168", "value": "{\"landingPage\":{\"headerTitle\":\"Log in or create an account\",\"headerDescription\":\"\",\"showProfessionalLogin\":false,\"showTermsAndPolicy\":false,\"showEmailMeLinkBtn\":false},\"passwordPage\":{\"signUp\":{\"headerTitle\":\"Add a password\",\"headerDescription\":\"Set a password to access your account on all your devices.\",\"showProfessionalLogin\":false,\"showTermsAndPolicy\":false,\"showEmailMeLinkBtn\":false},\"signIn\":{\"headerTitle\":\"Welcome back!\",\"headerDescription\":\"Please enter the password associated with {{email}} to continue.\",\"showProfessionalLogin\":false,\"showTermsAndPolicy\":false,\"showEmailMeLinkBtn\":false},\"WelcomeBack\":{\"headerTitle\":\"Welcome back!\",\"headerDescription\":\"We notice you haven't added the password yet. You'll need one to continue.\",\"showProfessionalLogin\":false,\"showTermsAndPolicy\":false,\"showEmailMeLinkBtn\":false}},\"marketingOptIn\":{\"headerTitle\":\"Thanks for signing up with realtor.com\",\"headerDescription\":\"Stay up to date with the latest tips, news, and insights on the real estate market.\",\"showProfessionalLogin\":false,\"showTermsAndPolicy\":false},\"forgotPassword\":{\"headerTitle\":\"Forgot Password?\",\"headerDescription\":\"No problem! We'll send an email with a link to reset your password.\",\"showProfessionalLogin\":false,\"showTermsAndPolicy\":false},\"almostDone\":{\"headerTitle\":\"Almost done!\",\"headerDescription\":\"Please check your inbox for password reset instructions. Don't see the email? Be sure to check your spam folder.\",\"showProfessionalLogin\":false,\"showTermsAndPolicy\":false},\"emailMeLink\":{\"headerTitle\":\"Email Me a Link\",\"headerDescription\":\"Enter your email address and we will send you a link. Follow the link to sign in automatically.\",\"showProfessionalLogin\":false,\"showTermsAndPolicy\":false},\"almostDoneEmailMe\":{\"headerTitle\":\"Almost done!\",\"headerDescription\":\"Please check your inbox for a sign-in link. Follow the link in the email message to be automatically signed in. Don't see the email? Be sure to check your spam folder.\",\"showProfessionalLogin\":false,\"showTermsAndPolicy\":false},\"show_custom_html\":false,\"containerName\":\"context_aware_web\",\"canSkipAddPassword\":false,\"buttonsDisplayOrder\":[{\"key\":\"continue\",\"text\":\"Continue\"}]}"}, {"id": "21242072297", "value": "{\"landingPage\":{\"headerTitle\":\"\u00bfEst\u00e1s listo para encontrar el hogar perfecto?\",\"headerDescription\":\"Inicia una sesi\u00f3n o reg\u00edstrate\",\"showProfessionalLogin\":false,\"showTermsAndPolicy\":true},\"passwordPage\":{\"signUp\":{\"headerTitle\":\"Recent Search Successfully Saved!!\",\"headerDescription\":\"Set a password to access your account on all your devices.\",\"showProfessionalLogin\":false,\"showTermsAndPolicy\":false},\"signIn\":{\"headerTitle\":\"Welcome back!\",\"headerDescription\":\"Please enter the password associated with {{email}} to continue.\",\"showProfessionalLogin\":false,\"showTermsAndPolicy\":false},\"WelcomeBack\":{\"headerTitle\":\"Welcome back!\",\"headerDescription\":\"We notice you haven't added the password yet. You'll need one to continue.\",\"showProfessionalLogin\":false,\"showTermsAndPolicy\":false}},\"marketingOptIn\":{\"headerTitle\":\"Thanks for signing up with realtor.com\",\"headerDescription\":\"Stay up to date with the latest tips, news, and insights on the real estate market.\",\"showProfessionalLogin\":false,\"showTermsAndPolicy\":false},\"forgotPassword\":{\"headerTitle\":\"Forgot Password?\",\"headerDescription\":\"No problem! We'll send an email with a link to reset your password.\",\"showProfessionalLogin\":false,\"showTermsAndPolicy\":false},\"almostDone\":{\"headerTitle\":\"Almost done!\",\"headerDescription\":\"Please check your inbox for password reset instructions. Don't see the email? Be sure to check your spam folder.\",\"showProfessionalLogin\":false,\"showTermsAndPolicy\":false},\"show_custom_html\":false,\"containerName\":\"context_aware_web\",\"canSkipAddPassword\":true,\"buttonsDisplayOrder\":[{\"key\":\"continue\",\"text\":\"Continue\"},{\"key\":\"google\",\"text\":\"Continue with Google\"},{\"key\":\"facebook\",\"text\":\"Continue with Facebook\"},{\"key\":\"apple\",\"text\":\"Continue with Apple\"}]}"}, {"id": "20626280128", "value": "{\"landingPage\":{\"headerTitle\":\"Log in or create an account to save your recent search\",\"headerDescription\":\"Save your favorite search and enjoy it from anywhere, on any of your devices\",\"showProfessionalLogin\":false,\"showTermsAndPolicy\":true},\"passwordPage\":{\"signUp\":{\"headerTitle\":\"Recent Search Successfully Saved!!\",\"headerDescription\":\"Set a password to access your account on all your devices.\",\"showProfessionalLogin\":false,\"showTermsAndPolicy\":false},\"signIn\":{\"headerTitle\":\"Welcome back!\",\"headerDescription\":\"Please enter the password associated with {{email}} to continue.\",\"showProfessionalLogin\":false,\"showTermsAndPolicy\":false},\"WelcomeBack\":{\"headerTitle\":\"Welcome back!\",\"headerDescription\":\"We notice you haven't added the password yet. You'll need one to continue.\",\"showProfessionalLogin\":false,\"showTermsAndPolicy\":false}},\"marketingOptIn\":{\"headerTitle\":\"Thanks for signing up with realtor.com\",\"headerDescription\":\"Stay up to date with the latest tips, news, and insights on the real estate market.\",\"showProfessionalLogin\":false,\"showTermsAndPolicy\":false},\"forgotPassword\":{\"headerTitle\":\"Forgot Password?\",\"headerDescription\":\"No problem! We'll send an email with a link to reset your password.\",\"showProfessionalLogin\":false,\"showTermsAndPolicy\":false},\"almostDone\":{\"headerTitle\":\"Almost done!\",\"headerDescription\":\"Please check your inbox for password reset instructions. Don't see the email? Be sure to check your spam folder.\",\"showProfessionalLogin\":false,\"showTermsAndPolicy\":false},\"show_custom_html\":false,\"containerName\":\"context_aware_web\",\"canSkipAddPassword\":true,\"buttonsDisplayOrder\":[{\"key\":\"continue\",\"text\":\"Continue\"},{\"key\":\"google\",\"text\":\"Continue with Google\"},{\"key\":\"facebook\",\"text\":\"Continue with Facebook\"},{\"key\":\"apple\",\"text\":\"Continue with Apple\"}]}"}, {"id": "21651650291", "value": "{\"landingPage\":{\"headerTitle\":\"Buying or renting together?\",\"headerDescription\":\"Register now to use special collaboration tools and find the right home together.\",\"showProfessionalLogin\":true,\"showTermsAndPolicy\":true,\"showEmailMeLinkBtn\":true},\"passwordPage\":{\"signUp\":{\"headerTitle\":\"Add a password\",\"headerDescription\":\"Set a password to access your account on all your devices.\",\"showProfessionalLogin\":false,\"showTermsAndPolicy\":false,\"showEmailMeLinkBtn\":true},\"signIn\":{\"headerTitle\":\"Welcome back!\",\"headerDescription\":\"Please enter the password associated with {{email}} to continue.\",\"showProfessionalLogin\":false,\"showTermsAndPolicy\":false,\"showEmailMeLinkBtn\":true},\"WelcomeBack\":{\"headerTitle\":\"Welcome back!\",\"headerDescription\":\"We notice you haven't added the password yet.You'll need one to continue.\",\"showProfessionalLogin\":false,\"showTermsAndPolicy\":false,\"showEmailMeLinkBtn\":true}},\"marketingOptIn\":{\"headerTitle\":\"Thanks for signing up with realtor.com\",\"headerDescription\":\"Stay up to date with the latest tips, news, and insights on the real estate market.\",\"showProfessionalLogin\":false,\"showTermsAndPolicy\":false},\"forgotPassword\":{\"headerTitle\":\"Forgot Password?\",\"headerDescription\":\"No problem! We'll send an email with a link to reset your password.\",\"showProfessionalLogin\":false,\"showTermsAndPolicy\":false},\"almostDone\":{\"headerTitle\":\"Almost done!\",\"headerDescription\":\"Please check your inbox for password reset instructions. Don't see the email? Be sure to check your spam folder.\",\"showProfessionalLogin\":false,\"showTermsAndPolicy\":false},\"emailMeLink\":{\"headerTitle\":\"Email Me a Link\",\"headerDescription\":\"Enter your email address and we will send you a link. Follow the link to sign in automatically.\",\"showProfessionalLogin\":false,\"showTermsAndPolicy\":false},\"almostDoneEmailMe\":{\"headerTitle\":\"Almost done!\",\"headerDescription\":\"Please check your inbox for a sign-in link. Follow the link in the email message to be automatically signed in. Don't see the email? Be sure to check your spam folder.\",\"showProfessionalLogin\":false,\"showTermsAndPolicy\":false},\"show_custom_html\":false,\"containerName\":\"context_aware_web\",\"canSkipAddPassword\":false,\"buttonsDisplayOrder\":[{\"key\":\"continue\",\"text\":\"Continue\"},{\"key\":\"google\",\"text\":\"Continue with Google\"},{\"key\":\"facebook\",\"text\":\"Continue with Facebook\"},{\"key\":\"apple\",\"text\":\"Continue with Apple\"},{\"key\":\"emailMe\",\"text\":\"Email Me a Link\"}]}"}, {"id": "21352850187", "value": "{\"landingPage\":{\"headerTitle\":\"Get more out of Realtor.com with a free account!\",\"headerDescription\":\"See new homes as soon as they hit the market.\",\"showProfessionalLogin\":true,\"showTermsAndPolicy\":true,\"showEmailMeLinkBtn\":true},\"passwordPage\":{\"signUp\":{\"headerTitle\":\"Add a password\",\"headerDescription\":\"Set a password to access your account on all your devices.\",\"showProfessionalLogin\":false,\"showTermsAndPolicy\":false,\"showEmailMeLinkBtn\":true},\"signIn\":{\"headerTitle\":\"Welcome back!\",\"headerDescription\":\"Please enter the password associated with {{email}} to continue.\",\"showProfessionalLogin\":false,\"showTermsAndPolicy\":false,\"showEmailMeLinkBtn\":true},\"WelcomeBack\":{\"headerTitle\":\"Welcome back!\",\"headerDescription\":\"We notice you haven't added the password yet.You'll need one to continue.\",\"showProfessionalLogin\":false,\"showTermsAndPolicy\":false,\"showEmailMeLinkBtn\":true}},\"marketingOptIn\":{\"headerTitle\":\"Thanks for signing up with realtor.com\",\"headerDescription\":\"Stay up to date with the latest tips, news, and insights on the real estate market.\",\"showProfessionalLogin\":false,\"showTermsAndPolicy\":false},\"forgotPassword\":{\"headerTitle\":\"Forgot Password?\",\"headerDescription\":\"No problem! We'll send an email with a link to reset your password.\",\"showProfessionalLogin\":false,\"showTermsAndPolicy\":false},\"almostDone\":{\"headerTitle\":\"Almost done!\",\"headerDescription\":\"Please check your inbox for password reset instructions. Don't see the email? Be sure to check your spam folder.\",\"showProfessionalLogin\":false,\"showTermsAndPolicy\":false},\"emailMeLink\":{\"headerTitle\":\"Email Me a Link\",\"headerDescription\":\"Enter your email address and we will send you a link. Follow the link to sign in automatically.\",\"showProfessionalLogin\":false,\"showTermsAndPolicy\":false},\"almostDoneEmailMe\":{\"headerTitle\":\"Almost done!\",\"headerDescription\":\"Please check your inbox for a sign-in link. Follow the link in the email message to be automatically signed in. Don't see the email? Be sure to check your spam folder.\",\"showProfessionalLogin\":false,\"showTermsAndPolicy\":false},\"show_custom_html\":false,\"containerName\":\"context_aware_web\",\"canSkipAddPassword\":false,\"buttonsDisplayOrder\":[{\"key\":\"continue\",\"text\":\"Continue\"},{\"key\":\"google\",\"text\":\"Continue with Google\"},{\"key\":\"facebook\",\"text\":\"Continue with Facebook\"},{\"key\":\"apple\",\"text\":\"Continue with Apple\"},{\"key\":\"emailMe\",\"text\":\"Email Me a Link\"}]}"}, {"id": "20626150155", "value": "{\"landingPage\":{\"headerTitle\":\"Log in or create an account to save your favorite homes\",\"headerDescription\":\"Save your favorite home and enjoy it from anywhere, on any of your devices.\",\"showProfessionalLogin\":false,\"showTermsAndPolicy\":true,\"showEmailMeLinkBtn\":true},\"passwordPage\":{\"signUp\":{\"headerTitle\":\"Add a password\",\"headerDescription\":\"Set a password to access your account on all your devices.\",\"showProfessionalLogin\":false,\"showTermsAndPolicy\":false,\"showEmailMeLinkBtn\":true},\"signIn\":{\"headerTitle\":\"Welcome back!\",\"headerDescription\":\"Please enter the password associated with {{email}} to continue.\",\"showProfessionalLogin\":false,\"showTermsAndPolicy\":false,\"showEmailMeLinkBtn\":true},\"WelcomeBack\":{\"headerTitle\":\"Welcome back!\",\"headerDescription\":\"We notice you haven't added the password yet.You'll need one to continue.\",\"showProfessionalLogin\":false,\"showTermsAndPolicy\":false,\"showEmailMeLinkBtn\":true}},\"marketingOptIn\":{\"headerTitle\":\"Thanks for signing up with realtor.com\",\"headerDescription\":\"Stay up to date with the latest tips, news, and insights on the real estate market.\",\"showProfessionalLogin\":false,\"showTermsAndPolicy\":false},\"forgotPassword\":{\"headerTitle\":\"Forgot Password?\",\"headerDescription\":\"No problem! We'll send an email with a link to reset your password.\",\"showProfessionalLogin\":false,\"showTermsAndPolicy\":false},\"almostDone\":{\"headerTitle\":\"Almost done!\",\"headerDescription\":\"Please check your inbox for password reset instructions.Don't see the email? Be sure to check your spam folder.\",\"showProfessionalLogin\":false,\"showTermsAndPolicy\":false},\"emailMeLink\":{\"headerTitle\":\"Email Me a Link\",\"headerDescription\":\"Enter your email address and we will send you a link. Follow the link to sign in automatically.\",\"showProfessionalLogin\":false,\"showTermsAndPolicy\":false},\"almostDoneEmailMe\":{\"headerTitle\":\"Almost done!\",\"headerDescription\":\"Please check your inbox for a sign-in link. Follow the link in the email message to be automatically signed in. Don't see the email? Be sure to check your spam folder.\",\"showProfessionalLogin\":false,\"showTermsAndPolicy\":false},\"show_custom_html\":false,\"containerName\":\"context_aware_web\",\"canSkipAddPassword\":true,\"buttonsDisplayOrder\":[{\"key\":\"continue\",\"text\":\"Continue\"},{\"key\":\"google\",\"text\":\"Continue with Google\"},{\"key\":\"facebook\",\"text\":\"Continue with Facebook\"},{\"key\":\"apple\",\"text\":\"Continue with Apple\"},{\"key\":\"emailMe\",\"text\":\"Email Me a Link\"}]}"}, {"id": "20640280014", "value": "{\"landingPage\":{\"headerTitle\":\"Log in or create an account to save your recent search\",\"headerDescription\":\"Save your favorite search and enjoy it from anywhere, on any of your devices.\",\"showProfessionalLogin\":false,\"showTermsAndPolicy\":true},\"passwordPage\":{\"signUp\":{\"headerTitle\":\"Add a password\",\"headerDescription\":\"Set a password to access your account on all your devices.\",\"showProfessionalLogin\":false,\"showTermsAndPolicy\":false},\"signIn\":{\"headerTitle\":\"Welcome back!\",\"headerDescription\":\"Please enter the password associated with {{email}} to continue.\",\"showProfessionalLogin\":false,\"showTermsAndPolicy\":false},\"WelcomeBack\":{\"headerTitle\":\"Welcome back!\",\"headerDescription\":\"We notice you haven't added the password yet.You'll need one to continue.\",\"showProfessionalLogin\":false,\"showTermsAndPolicy\":false}},\"marketingOptIn\":{\"headerTitle\":\"Thanks for signing up with realtor.com\",\"headerDescription\":\"Stay up to date with the latest tips, news, and insights on the real estate market.\",\"showProfessionalLogin\":false,\"showTermsAndPolicy\":false},\"forgotPassword\":{\"headerTitle\":\"Forgot Password?\",\"headerDescription\":\"No problem! We'll send an email with a link to reset your password.\",\"showProfessionalLogin\":false,\"showTermsAndPolicy\":false},\"almostDone\":{\"headerTitle\":\"Almost done!\",\"headerDescription\":\"Please check your inbox for password reset instructions.Don't see the email? Be sure to check your spam folder.\",\"showProfessionalLogin\":false,\"showTermsAndPolicy\":false},\"show_custom_html\":false,\"containerName\":\"context_aware_web\",\"canSkipAddPassword\":true,\"buttonsDisplayOrder\":[{\"key\":\"continue\",\"text\":\"Continue\"},{\"key\":\"google\",\"text\":\"Continue with Google\"},{\"key\":\"facebook\",\"text\":\"Continue with Facebook\"},{\"key\":\"apple\",\"text\":\"Continue with Apple\"}]}"}, {"id": "21134770537", "value": "{\"landingPage\":{\"headerTitle\":\"Get the latest news on celebrity homes in your inbox\",\"headerDescription\":\"Log in or create an account\",\"showProfessionalLogin\":true,\"showTermsAndPolicy\":true,\"showEmailMeLinkBtn\":true},\"passwordPage\":{\"signUp\":{\"headerTitle\":\"Add a password\",\"headerDescription\":\"Set a password to access your account on all your devices.\",\"showProfessionalLogin\":false,\"showTermsAndPolicy\":false,\"showEmailMeLinkBtn\":true},\"signIn\":{\"headerTitle\":\"Welcome back!\",\"headerDescription\":\"Please enter the password associated with {{email}} to continue.\",\"showProfessionalLogin\":false,\"showTermsAndPolicy\":false,\"showEmailMeLinkBtn\":true},\"WelcomeBack\":{\"headerTitle\":\"Welcome back!\",\"headerDescription\":\"We notice you haven't added the password yet.You'll need one to continue.\",\"showProfessionalLogin\":false,\"showTermsAndPolicy\":false,\"showEmailMeLinkBtn\":true}},\"marketingOptIn\":{\"headerTitle\":\"Thanks for signing up with realtor.com\",\"headerDescription\":\"Stay up to date with the latest tips, news, and insights on the real estate market.\",\"showProfessionalLogin\":false,\"showTermsAndPolicy\":false},\"forgotPassword\":{\"headerTitle\":\"Forgot Password?\",\"headerDescription\":\"No problem! We'll send an email with a link to reset your password.\",\"showProfessionalLogin\":false,\"showTermsAndPolicy\":false},\"almostDone\":{\"headerTitle\":\"Almost done!\",\"headerDescription\":\"Please check your inbox for password reset instructions. Don't see the email? Be sure to check your spam folder.\",\"showProfessionalLogin\":false,\"showTermsAndPolicy\":false},\"emailMeLink\":{\"headerTitle\":\"Email Me a Link\",\"headerDescription\":\"Enter your email address and we will send you a link. Follow the link to sign in automatically.\",\"showProfessionalLogin\":false,\"showTermsAndPolicy\":false},\"almostDoneEmailMe\":{\"headerTitle\":\"Almost done!\",\"headerDescription\":\"Please check your inbox for a sign-in link. Follow the link in the email message to be automatically signed in. Don't see the email? Be sure to check your spam folder.\",\"showProfessionalLogin\":false,\"showTermsAndPolicy\":false},\"show_custom_html\":false,\"containerName\":\"context_aware_web\",\"canSkipAddPassword\":false,\"buttonsDisplayOrder\":[{\"key\":\"continue\",\"text\":\"Continue\"},{\"key\":\"google\",\"text\":\"Continue with Google\"},{\"key\":\"facebook\",\"text\":\"Continue with Facebook\"},{\"key\":\"apple\",\"text\":\"Continue with Apple\"},{\"key\":\"emailMe\",\"text\":\"Email Me a Link\"}]}"}, {"id": "21260940456", "value": "{\"landingPage\":{\"headerTitle\":\"Get your free account today!\",\"headerDescription\":\"Supercharge your experience with a free account.\",\"showProfessionalLogin\":true,\"showTermsAndPolicy\":true,\"showEmailMeLinkBtn\":true},\"passwordPage\":{\"signUp\":{\"headerTitle\":\"Add a password\",\"headerDescription\":\"Set a password to access your account on all your devices.\",\"showProfessionalLogin\":false,\"showTermsAndPolicy\":false,\"showEmailMeLinkBtn\":true},\"signIn\":{\"headerTitle\":\"Welcome back!\",\"headerDescription\":\"Please enter the password associated with {{email}} to continue.\",\"showProfessionalLogin\":false,\"showTermsAndPolicy\":false,\"showEmailMeLinkBtn\":true},\"WelcomeBack\":{\"headerTitle\":\"Welcome back!\",\"headerDescription\":\"We notice you haven't added the password yet.You'll need one to continue.\",\"showProfessionalLogin\":false,\"showTermsAndPolicy\":false,\"showEmailMeLinkBtn\":true}},\"marketingOptIn\":{\"headerTitle\":\"Thanks for signing up with realtor.com\",\"headerDescription\":\"Stay up to date with the latest tips, news, and insights on the real estate market.\",\"showProfessionalLogin\":false,\"showTermsAndPolicy\":false},\"forgotPassword\":{\"headerTitle\":\"Forgot Password?\",\"headerDescription\":\"No problem! We'll send an email with a link to reset your password.\",\"showProfessionalLogin\":false,\"showTermsAndPolicy\":false},\"almostDone\":{\"headerTitle\":\"Almost done!\",\"headerDescription\":\"Please check your inbox for password reset instructions. Don't see the email? Be sure to check your spam folder.\",\"showProfessionalLogin\":false,\"showTermsAndPolicy\":false},\"emailMeLink\":{\"headerTitle\":\"Email Me a Link\",\"headerDescription\":\"Enter your email address and we will send you a link. Follow the link to sign in automatically.\",\"showProfessionalLogin\":false,\"showTermsAndPolicy\":false},\"almostDoneEmailMe\":{\"headerTitle\":\"Almost done!\",\"headerDescription\":\"Please check your inbox for a sign-in link. Follow the link in the email message to be automatically signed in. Don't see the email? Be sure to check your spam folder.\",\"showProfessionalLogin\":false,\"showTermsAndPolicy\":false},\"show_custom_html\":false,\"containerName\":\"context_aware_web\",\"canSkipAddPassword\":false,\"buttonsDisplayOrder\":[{\"key\":\"continue\",\"text\":\"Continue\"},{\"key\":\"google\",\"text\":\"Continue with Google\"},{\"key\":\"facebook\",\"text\":\"Continue with Facebook\"},{\"key\":\"apple\",\"text\":\"Continue with Apple\"},{\"key\":\"emailMe\",\"text\":\"Email Me a Link\"}]}"}, {"id": "21604363711", "value": "{\"landingPage\":{\"headerTitle\":\"Be the first to know\",\"headerDescription\":\"Register to save your search and get alerts for new listings that fit your needs.\",\"showProfessionalLogin\":true,\"showTermsAndPolicy\":true,\"showEmailMeLinkBtn\":true},\"passwordPage\":{\"signUp\":{\"headerTitle\":\"Add a password\",\"headerDescription\":\"Set a password to access your account on all your devices.\",\"showProfessionalLogin\":false,\"showTermsAndPolicy\":false,\"showEmailMeLinkBtn\":true},\"signIn\":{\"headerTitle\":\"Welcome back!\",\"headerDescription\":\"Please enter the password associated with {{email}} to continue.\",\"showProfessionalLogin\":false,\"showTermsAndPolicy\":false,\"showEmailMeLinkBtn\":true},\"WelcomeBack\":{\"headerTitle\":\"Welcome back!\",\"headerDescription\":\"We notice you haven't added the password yet.You'll need one to continue.\",\"showProfessionalLogin\":false,\"showTermsAndPolicy\":false,\"showEmailMeLinkBtn\":true}},\"marketingOptIn\":{\"headerTitle\":\"Thanks for signing up with realtor.com\",\"headerDescription\":\"Stay up to date with the latest tips, news, and insights on the real estate market.\",\"showProfessionalLogin\":false,\"showTermsAndPolicy\":false},\"forgotPassword\":{\"headerTitle\":\"Forgot Password?\",\"headerDescription\":\"No problem! We'll send an email with a link to reset your password.\",\"showProfessionalLogin\":false,\"showTermsAndPolicy\":false},\"almostDone\":{\"headerTitle\":\"Almost done!\",\"headerDescription\":\"Please check your inbox for password reset instructions. Don't see the email? Be sure to check your spam folder.\",\"showProfessionalLogin\":false,\"showTermsAndPolicy\":false},\"emailMeLink\":{\"headerTitle\":\"Email Me a Link\",\"headerDescription\":\"Enter your email address and we will send you a link. Follow the link to sign in automatically.\",\"showProfessionalLogin\":false,\"showTermsAndPolicy\":false},\"almostDoneEmailMe\":{\"headerTitle\":\"Almost done!\",\"headerDescription\":\"Please check your inbox for a sign-in link. Follow the link in the email message to be automatically signed in. Don't see the email? Be sure to check your spam folder.\",\"showProfessionalLogin\":false,\"showTermsAndPolicy\":false},\"show_custom_html\":false,\"containerName\":\"context_aware_web\",\"canSkipAddPassword\":false,\"buttonsDisplayOrder\":[{\"key\":\"continue\",\"text\":\"Continue\"},{\"key\":\"google\",\"text\":\"Continue with Google\"},{\"key\":\"facebook\",\"text\":\"Continue with Facebook\"},{\"key\":\"apple\",\"text\":\"Continue with Apple\"},{\"key\":\"emailMe\",\"text\":\"Email Me a Link\"}]}"}, {"id": "20649000172", "value": "{\"landingPage\":{\"headerTitle\":\"Log in or create an account\",\"headerDescription\":\"\",\"showProfessionalLogin\":true,\"showTermsAndPolicy\":true,\"showEmailMeLinkBtn\":true},\"passwordPage\":{\"signUp\":{\"headerTitle\":\"Add a password\",\"headerDescription\":\"Set a password to access your account on all your devices.\",\"showProfessionalLogin\":false,\"showTermsAndPolicy\":false,\"showEmailMeLinkBtn\":true},\"signIn\":{\"headerTitle\":\"Welcome back!\",\"headerDescription\":\"Please enter the password associated with {{email}} to continue.\",\"showProfessionalLogin\":false,\"showTermsAndPolicy\":false,\"showEmailMeLinkBtn\":true},\"WelcomeBack\":{\"headerTitle\":\"Welcome back!\",\"headerDescription\":\"We notice you haven't added the password yet.You'll need one to continue.\",\"showProfessionalLogin\":false,\"showTermsAndPolicy\":false,\"showEmailMeLinkBtn\":true}},\"success\":{\"signUp\":{\"headerTitle\":\"Sign-up successful!\",\"headerDescription\":\"You now have access to more from Realtor.com!\",\"show\":true,\"dynamicHtml\":\"<html><head></head><body><div><a href=\\\"https://www.realtor.com/sell/sellers-marketplace\\\"><img src=\\\"https://d32kodjovuzxj9.cloudfront.net/images/img-selloptions.svg\\\"alt = \\\"Seller Marketplace\\\" width=\\\"300\\\" height=\\\"200\\\"></a></div><div style=\\\"width: 100%; text-align: center;\\\">Do you have a home to sell? If so, check out our <a href=\\\"https://www.realtor.com/sell/sellers-marketplace\\\">Seller's Marketplace</a>.</li></div><div style=\\\"width: 100%; height: 15px; border-bottom: 1px solid black; text-align: center; margin: 10px 0px 24px;\\\"><span style=\\\"font-size: 14px; background-color: rgb(255, 255, 255); padding: 4px 10px 0px; display: inline-block; margin: 0px;\\\">or</span></div></body></html>\"},\"signIn\":{\"headerTitle\":\"Sign-in successful!\",\"show\":true,\"headerDescription\":\"You now have access to more from Realtor.com!\",\"dynamicHtml\":\"<html><head></head><body><div><a href=\\\"https://www.realtor.com/sell/sellers-marketplace\\\"><img src=\\\"https://d32kodjovuzxj9.cloudfront.net/images/img-selloptions.svg\\\"alt = \\\"Seller Marketplace\\\" width=\\\"300\\\" height=\\\"200\\\"></a></div><div style=\\\"width: 100%; text-align: center;\\\">Do you have a home to sell? If so, check out our <a href=\\\"https://www.realtor.com/sell/sellers-marketplace\\\">Seller's Marketplace</a>.</li></div><div style=\\\"width: 100%; height: 15px; border-bottom: 1px solid black; text-align: center; margin: 10px 0px 24px;\\\"><span style=\\\"font-size: 14px; background-color: rgb(255, 255, 255); padding: 4px 10px 0px; display: inline-block; margin: 0px;\\\">or</span></div></body></html>\"}},\"marketingOptIn\":{\"headerTitle\":\"Thanks for signing up with realtor.com\",\"headerDescription\":\"Stay up to date with the latest tips, news, and insights on the real estate market.\",\"showProfessionalLogin\":false,\"showTermsAndPolicy\":false},\"forgotPassword\":{\"headerTitle\":\"Forgot Password?\",\"headerDescription\":\"No problem! We'll send an email with a link to reset your password.\",\"showProfessionalLogin\":false,\"showTermsAndPolicy\":false},\"almostDone\":{\"headerTitle\":\"Almost done!\",\"headerDescription\":\"Please check your inbox for password reset instructions. Don't see the email? Be sure to check your spam folder.\",\"showProfessionalLogin\":false,\"showTermsAndPolicy\":false},\"emailMeLink\":{\"headerTitle\":\"Email Me a Link\",\"headerDescription\":\"Enter your email address and we will send you a link. Follow the link to sign in automatically.\",\"showProfessionalLogin\":false,\"showTermsAndPolicy\":false},\"almostDoneEmailMe\":{\"headerTitle\":\"Almost done!\",\"headerDescription\":\"Please check your inbox for a sign-in link. Follow the link in the email message to be automatically signed in. Don't see the email? Be sure to check your spam folder.\",\"showProfessionalLogin\":false,\"showTermsAndPolicy\":false},\"show_custom_html\":false,\"containerName\":\"context_aware_web\",\"canSkipAddPassword\":false,\"buttonsDisplayOrder\":[{\"key\":\"continue\",\"text\":\"Continue\"},{\"key\":\"google\",\"text\":\"Continue with Google\"},{\"key\":\"facebook\",\"text\":\"Continue with Facebook\"},{\"key\":\"apple\",\"text\":\"Continue with Apple\"},{\"key\":\"emailMe\",\"text\":\"Email Me a Link\"}]}"}, {"id": "20715381351", "value": "{\"landingPage\":{\"headerTitle\":\"Log in or create an account\",\"headerDescription\":\"Use your account to hide, save and manage homes to help you more easily search.\",\"showProfessionalLogin\":false,\"showTermsAndPolicy\":true,\"showEmailMeLinkBtn\":true},\"passwordPage\":{\"signUp\":{\"headerTitle\":\"Add a password\",\"headerDescription\":\"Set a password to access your account on all your devices.\",\"showProfessionalLogin\":false,\"showTermsAndPolicy\":false,\"showEmailMeLinkBtn\":true},\"signIn\":{\"headerTitle\":\"Welcome back!\",\"headerDescription\":\"Please enter the password associated with {{email}} to continue.\",\"showProfessionalLogin\":false,\"showTermsAndPolicy\":false,\"showEmailMeLinkBtn\":true},\"WelcomeBack\":{\"headerTitle\":\"Welcome back!\",\"headerDescription\":\"We notice you haven't added the password yet.You'll need one to continue.\",\"showProfessionalLogin\":false,\"showTermsAndPolicy\":false,\"showEmailMeLinkBtn\":true}},\"marketingOptIn\":{\"headerTitle\":\"Thanks for signing up with realtor.com\",\"headerDescription\":\"Stay up to date with the latest tips, news, and insights on the real estate market.\",\"showProfessionalLogin\":false,\"showTermsAndPolicy\":false},\"forgotPassword\":{\"headerTitle\":\"Forgot Password?\",\"headerDescription\":\"No problem! We'll send an email with a link to reset your password.\",\"showProfessionalLogin\":false,\"showTermsAndPolicy\":false},\"almostDone\":{\"headerTitle\":\"Almost done!\",\"headerDescription\":\"Please check your inbox for password reset instructions.Don't see the email? Be sure to check your spam folder.\",\"showProfessionalLogin\":false,\"showTermsAndPolicy\":false},\"emailMeLink\":{\"headerTitle\":\"Email Me a Link\",\"headerDescription\":\"Enter your email address and we will send you a link. Follow the link to sign in automatically.\",\"showProfessionalLogin\":false,\"showTermsAndPolicy\":false},\"almostDoneEmailMe\":{\"headerTitle\":\"Almost done!\",\"headerDescription\":\"Please check your inbox for a sign-in link. Follow the link in the email message to be automatically signed in. Don't see the email? Be sure to check your spam folder.\",\"showProfessionalLogin\":false,\"showTermsAndPolicy\":false},\"show_custom_html\":false,\"containerName\":\"context_aware_web\",\"canSkipAddPassword\":true,\"buttonsDisplayOrder\":[{\"key\":\"continue\",\"text\":\"Continue\"},{\"key\":\"google\",\"text\":\"Continue with Google\"},{\"key\":\"facebook\",\"text\":\"Continue with Facebook\"},{\"key\":\"apple\",\"text\":\"Continue with Apple\"},{\"key\":\"emailMe\",\"text\":\"Email Me a Link\"}]}"}], "id": "20545661887", "key": "V1", "featureEnabled": true}], "id": "20538072546", "key": "RAAS_WEB_DYNAMIC", "layerId": "20547582139", "trafficAllocation": [{"entityId": "20545661887", "endOfRange": 5000}, {"entityId": "20545661887", "endOfRange": 10000}], "forcedVariations": {}}], "version": "4", "audiences": [{"conditions": "[\"or\", {\"match\": \"exact\", \"name\": \"$opt_dummy_attribute\", \"type\": \"custom_attribute\", \"value\": \"$opt_dummy_value\"}]", "id": "$opt_dummy_audience", "name": "Optimizely-Generated Audience for Backwards Compatibility"}], "anonymizeIP": false, "sdkKey": "6HLU9D1A4w7y6kJyj6YYbj", "attributes": [], "botFiltering": false, "accountId": "329591024", "events": [{"experimentIds": ["20538072546"], "id": "20551392249", "key": "contextaware"}], "revision": "350"}